{
  "books": [
    {
      "title": "The Wait: A Powerful Practice for Finding the Love of Your Life and the Life You Love",
      "url": "https://www.goodreads.com/book/show/23492536-the-wait",
      "id": "43082754",
      "cover_url": "https://images-na.ssl-images-amazon.com/images/S/compressed.photo.goodreads.com/books/1454256521i/23492536.jpg",
      "authors": [
        "DeVon Franklin"
      ],
      "genres": [
        "christian",
        "relationships",
        "self-help",
        "non-fiction",
        "religion",
        "spirituality",
        "faith"
      ],
      "rating": 4.22,
      "ratings": 2626,
      "reviews": 321
    },
    {
      "title": "Paved Paradise: How Parking Explains the World",
      "url": "https://www.goodreads.com/book/show/63329951-paved-paradise",
      "id": "99249851",
      "cover_url": "https://images-na.ssl-images-amazon.com/images/S/compressed.photo.goodreads.com/books/1671685274i/63329951.jpg",
      "authors": [
        "Henry Grabar"
      ],
      "genres": [
        "non-fiction",
        "history",
        "urbanism",
        "urban-planning",
        "politics",
        "sociology",
        "economics"
      ],
      "rating": 4.23,
      "ratings": 2626,
      "reviews": 433
    },
    {
      "title": "The Smallest Lights in the Universe: A Memoir",
      "url": "https://www.goodreads.com/book/show/43982439-the-smallest-lights-in-the-universe",
      "id": "68379333",
      "cover_url": "https://images-na.ssl-images-amazon.com/images/S/compressed.photo.goodreads.com/books/1555941828i/43982439.jpg",
      "authors": [
        "Sara  Seager"
      ],
      "genres": [
        "memoir",
        "non-fiction",
        "science",
        "biography",
        "audiobook",
        "biography-memoir",
        "space"
      ],
      "rating": 4.12,
      "ratings": 2626,
      "reviews": 448
    },
    {
      "title": "A Quest for Godliness",
      "url": "https://www.goodreads.com/book/show/549080.A_Quest_for_Godliness",
      "id": "536328",
      "cover_url": "https://images-na.ssl-images-amazon.com/images/S/compressed.photo.goodreads.com/books/1348806560i/549080.jpg",
      "authors": [
        "J.I. Packer"
      ],
      "genres": [
        "theology",
        "christian",
        "christian-living",
        "church-history",
        "history",
        "christianity",
        "non-fiction"
      ],
      "rating": 4.34,
      "ratings": 2625,
      "reviews": 112
    },
    {
      "title": "The Ancient Secret of the Flower of Life: Volume 1",
      "url": "https://www.goodreads.com/book/show/96630.The_Ancient_Secret_of_the_Flower_of_Life",
      "id": "93138",
      "cover_url": "https://images-na.ssl-images-amazon.com/images/S/compressed.photo.goodreads.com/books/1313358628i/96630.jpg",
      "authors": [
        "Drunvalo Melchizedek"
      ],
      "genres": [
        "spirituality",
        "non-fiction",
        "metaphysics",
        "science",
        "occult",
        "new-age",
        "philosophy"
      ],
      "rating": 4.28,
      "ratings": 2625,
      "reviews": 157
    },
    {
      "title": "Childhood Disrupted: How Your Biography Becomes Your Biology, and How You Can Heal",
      "url": "https://www.goodreads.com/book/show/23492704-childhood-disrupted",
      "id": "43082877",
      "cover_url": "https://images-na.ssl-images-amazon.com/images/S/compressed.photo.goodreads.com/books/1436129295i/23492704.jpg",
      "authors": [
        "Donna Jackson Nakazawa"
      ],
      "genres": [
        "psychology",
        "non-fiction",
        "self-help",
        "mental-health",
        "health",
        "parenting",
        "science"
      ],
      "rating": 4.27,
      "ratings": 2624,
      "reviews": 290
    },
    {
      "title": "The Life of Saint Teresa of Ávila by Herself",
      "url": "https://www.goodreads.com/book/show/731697.The_Life_of_Saint_Teresa_of_vila_by_Herself",
      "id": "395964",
      "cover_url": "https://images-na.ssl-images-amazon.com/images/S/compressed.photo.goodreads.com/books/1177779930i/731697.jpg",
      "authors": [
        "Teresa of Ávila"
      ],
      "genres": [
        "religion",
        "biography",
        "catholic",
        "non-fiction",
        "spirituality",
        "classics",
        "christianity"
      ],
      "rating": 4.14,
      "ratings": 2624,
      "reviews": 221
    },
    {
      "title": "Never Turn Your Back on an Angus Cow: My Life As a Country Vet",
      "url": "https://www.goodreads.com/book/show/18693660-never-turn-your-back-on-an-angus-cow",
      "id": "26542206",
      "cover_url": "https://images-na.ssl-images-amazon.com/images/S/compressed.photo.goodreads.com/books/1403184126i/18693660.jpg",
      "authors": [
        "Jan Pol"
      ],
      "genres": [
        "non-fiction",
        "animals",
        "biography",
        "memoir",
        "autobiography",
        "humor",
        "biography-memoir"
      ],
      "rating": 4.25,
      "ratings": 2623,
      "reviews": 403
    },
    {
      "title": "A Molecule Away from Madness: Tales of the Hijacked Brain",
      "url": "https://www.goodreads.com/book/show/58085250-a-molecule-away-from-madness",
      "id": "91033974",
      "cover_url": "https://images-na.ssl-images-amazon.com/images/S/compressed.photo.goodreads.com/books/1641271142i/58085250.jpg",
      "authors": [
        "Sara Manning Peskin"
      ],
      "genres": [
        "science",
        "non-fiction",
        "psychology",
        "medicine",
        "neuroscience",
        "medical",
        "mental-health"
      ],
      "rating": 4.22,
      "ratings": 2623,
      "reviews": 333
    },
    {
      "title": "Wonderland Avenue: Tales of Glamour and Excess",
      "url": "https://www.goodreads.com/book/show/141495.Wonderland_Avenue",
      "id": "990511",
      "cover_url": "https://images-na.ssl-images-amazon.com/images/S/compressed.photo.goodreads.com/books/1172125275i/141495.jpg",
      "authors": [
        "Danny Sugerman"
      ],
      "genres": [
        "music",
        "biography",
        "non-fiction",
        "memoir",
        "autobiography",
        "biography-memoir",
        "classics"
      ],
      "rating": 4.25,
      "ratings": 2623,
      "reviews": 160
    },
    {
      "title": "Python Crash Course: A Hands-On, Project-Based Introduction to Programming",
      "url": "https://www.goodreads.com/book/show/23241059-python-crash-course",
      "id": "42784657",
      "cover_url": "https://images-na.ssl-images-amazon.com/images/S/compressed.photo.goodreads.com/books/1418765169i/23241059.jpg",
      "authors": [
        "Eric Matthes"
      ],
      "genres": [
        "programming",
        "non-fiction",
        "computer-science",
        "coding",
        "technology",
        "reference",
        "technical"
      ],
      "rating": 4.36,
      "ratings": 2623,
      "reviews": 256
    },
    {
      "title": "Why You Should Read Children's Books, Even Though You Are So Old and Wise",
      "url": "https://www.goodreads.com/book/show/44244323-why-you-should-read-children-s-books-even-though-you-are-so-old-and-wis",
      "id": "68772876",
      "cover_url": "https://images-na.ssl-images-amazon.com/images/S/compressed.photo.goodreads.com/books/1560803941i/44244323.jpg",
      "authors": [
        "Katherine Rundell"
      ],
      "genres": [
        "non-fiction",
        "books-about-books",
        "essays",
        "childrens",
        "adult",
        "literature",
        "writing"
      ],
      "rating": 4.11,
      "ratings": 2622,
      "reviews": 425
    },
    {
      "title": "The New Testament and the People of God",
      "url": "https://www.goodreads.com/book/show/410758.The_New_Testament_and_the_People_of_God",
      "id": "4030",
      "cover_url": "https://images-na.ssl-images-amazon.com/images/S/compressed.photo.goodreads.com/books/1421264779i/410758.jpg",
      "authors": [
        "N.T. Wright"
      ],
      "genres": [
        "theology",
        "religion",
        "history",
        "christianity",
        "christian",
        "non-fiction",
        "new-testament"
      ],
      "rating": 4.39,
      "ratings": 2622,
      "reviews": 191
    },
    {
      "title": "Washed and Waiting: Reflections on Christian Faithfulness and Homosexuality",
      "url": "https://www.goodreads.com/book/show/7994726-washed-and-waiting",
      "id": "12489002",
      "cover_url": "https://images-na.ssl-images-amazon.com/images/S/compressed.photo.goodreads.com/books/1327998086i/7994726.jpg",
      "authors": [
        "Wesley Hill"
      ],
      "genres": [
        "christian",
        "non-fiction",
        "sexuality",
        "theology",
        "christianity",
        "religion",
        "memoir"
      ],
      "rating": 4.23,
      "ratings": 2622,
      "reviews": 353
    },
    {
      "title": "The Lakota Way: Stories and Lessons for Living",
      "url": "https://www.goodreads.com/book/show/305508.The_Lakota_Way",
      "id": "296508",
      "cover_url": "https://images-na.ssl-images-amazon.com/images/S/compressed.photo.goodreads.com/books/1348456249i/305508.jpg",
      "authors": [
        "Joseph M. Marshall III"
      ],
      "genres": [
        "non-fiction",
        "history",
        "philosophy",
        "spirituality",
        "religion",
        "audiobook",
        "mythology"
      ],
      "rating": 4.36,
      "ratings": 2622,
      "reviews": 273
    },
    {
      "title": "Gerrard: My Autobiography",
      "url": "https://www.goodreads.com/book/show/1527043.Gerrard",
      "id": "1518998",
      "cover_url": "https://images-na.ssl-images-amazon.com/images/S/compressed.photo.goodreads.com/books/1320388280i/1527043.jpg",
      "authors": [
        "Steven Gerrard"
      ],
      "genres": [
        "biography",
        "football",
        "sports",
        "non-fiction",
        "autobiography",
        "soccer",
        "memoir"
      ],
      "rating": 4.06,
      "ratings": 2621,
      "reviews": 109
    },
    {
      "title": "The Frackers: The Outrageous Inside Story of the New Billionaire Wildcatters",
      "url": "https://www.goodreads.com/book/show/17707481-the-frackers",
      "id": "24757009",
      "cover_url": "https://images-na.ssl-images-amazon.com/images/S/compressed.photo.goodreads.com/books/1372054121i/17707481.jpg",
      "authors": [
        "Gregory Zuckerman"
      ],
      "genres": [
        "business",
        "non-fiction",
        "history",
        "economics",
        "environment",
        "finance",
        "biography"
      ],
      "rating": 4,
      "ratings": 2618,
      "reviews": 199
    },
    {
      "title": "Know Why You Believe",
      "url": "https://www.goodreads.com/book/show/1043837.Know_Why_You_Believe",
      "id": "1030245",
      "cover_url": "https://images-na.ssl-images-amazon.com/images/S/compressed.photo.goodreads.com/books/1387668312i/1043837.jpg",
      "authors": [
        "Paul E. Little"
      ],
      "genres": [
        "christian",
        "non-fiction",
        "theology",
        "religion",
        "christianity",
        "faith",
        "christian-living"
      ],
      "rating": 4.03,
      "ratings": 2616,
      "reviews": 114
    },
    {
      "title": "Holy Hygge: Creating a Place for People to Gather and the Gospel to Grow",
      "url": "https://www.goodreads.com/book/show/60447467-holy-hygge",
      "id": "95257606",
      "cover_url": "https://images-na.ssl-images-amazon.com/images/S/compressed.photo.goodreads.com/books/1646452321i/60447467.jpg",
      "authors": [
        "Jamie Erickson"
      ],
      "genres": [
        "christian",
        "non-fiction",
        "faith",
        "christian-living",
        "christianity",
        "spirituality",
        "christian-non-fiction"
      ],
      "rating": 4.15,
      "ratings": 2615,
      "reviews": 349
    },
    {
      "title": "All of the Marvels: A Journey to the Ends of the Biggest Story Ever Told",
      "url": "https://www.goodreads.com/book/show/56913465-all-of-the-marvels",
      "id": "89005662",
      "cover_url": "https://images-na.ssl-images-amazon.com/images/S/compressed.photo.goodreads.com/books/1619419337i/56913465.jpg",
      "authors": [
        "Douglas Wolk"
      ],
      "genres": [
        "non-fiction",
        "comics",
        "history",
        "marvel",
        "superheroes",
        "pop-culture",
        "books-about-books"
      ],
      "rating": 4.01,
      "ratings": 2614,
      "reviews": 527
    },
    {
      "title": "The Immortal Game: A History of Chess, or How 32 Carved Pieces on a Board Illuminated Our Understanding of War, Art, Science and the Human Brain",
      "url": "https://www.goodreads.com/book/show/85083.The_Immortal_Game",
      "id": "2341058",
      "cover_url": "https://images-na.ssl-images-amazon.com/images/S/compressed.photo.goodreads.com/books/1171058927i/85083.jpg",
      "authors": [
        "David Shenk"
      ],
      "genres": [
        "chess",
        "history",
        "non-fiction",
        "games",
        "sports",
        "science",
        "philosophy"
      ],
      "rating": 4,
      "ratings": 2613,
      "reviews": 321
    },
    {
      "title": "Notes on a Foreign Country: An American Abroad in a Post-American World",
      "url": "https://www.goodreads.com/book/show/31450559-notes-on-a-foreign-country",
      "id": "52153456",
      "cover_url": "https://images-na.ssl-images-amazon.com/images/S/compressed.photo.goodreads.com/books/1497854609i/31450559.jpg",
      "authors": [
        "Suzy Hansen"
      ],
      "genres": [
        "non-fiction",
        "memoir",
        "travel",
        "politics",
        "history",
        "journalism",
        "audiobook"
      ],
      "rating": 4.05,
      "ratings": 2613,
      "reviews": 456
    },
    {
      "title": "The Person You Mean to Be: How Good People Fight Bias",
      "url": "https://www.goodreads.com/book/show/39352190-the-person-you-mean-to-be",
      "id": "61011335",
      "cover_url": "https://images-na.ssl-images-amazon.com/images/S/compressed.photo.goodreads.com/books/1521782476i/39352190.jpg",
      "authors": [
        "Dolly Chugh"
      ],
      "genres": [
        "non-fiction",
        "psychology",
        "self-help",
        "social-justice",
        "race",
        "business",
        "personal-development"
      ],
      "rating": 4.29,
      "ratings": 2613,
      "reviews": 389
    },
    {
      "title": "A Wedding Thing",
      "url": "https://www.goodreads.com/book/show/46146989-a-wedding-thing",
      "id": "71096608",
      "cover_url": "https://images-na.ssl-images-amazon.com/images/S/compressed.photo.goodreads.com/books/1559675958i/46146989.jpg",
      "authors": [
        "Shea Serrano"
      ],
      "genres": [
        "short-stories",
        "non-fiction",
        "romance",
        "memoir",
        "audiobook",
        "contemporary",
        "biography"
      ],
      "rating": 4.01,
      "ratings": 2613,
      "reviews": 249
    }
  ]
}
