{
  "books": [
    {
      "title": "Ajin: Demi-Human, Vol. 6",
      "url": "https://www.goodreads.com/book/show/23995547-ajin",
      "id": "43596199",
      "cover_url": "https://images-na.ssl-images-amazon.com/images/S/compressed.photo.goodreads.com/books/1437027390i/23995547.jpg",
      "authors": [
        "Gamon Sakurai"
      ],
      "genres": [
        "manga",
        "horror",
        "fantasy",
        "comics",
        "seinen",
        "graphic-novels",
        "thriller"
      ],
      "rating": 4.24,
      "ratings": 2006,
      "reviews": 102
    },
    {
      "title": "20th Century Boys 16",
      "url": "https://www.goodreads.com/book/show/1725525.20th_Century_Boys_16",
      "id": "1722934",
      "cover_url": "https://images-na.ssl-images-amazon.com/images/S/compressed.photo.goodreads.com/books/1344499552i/1725525.jpg",
      "authors": [
        "Naoki Urasawa"
      ],
      "genres": [
        "manga",
        "comics",
        "science-fiction",
        "mystery",
        "seinen",
        "graphic-novels",
        "fiction"
      ],
      "rating": 4.43,
      "ratings": 2006,
      "reviews": 74
    },
    {
      "title": "20th Century Boys, 19",
      "url": "https://www.goodreads.com/book/show/3183874-20th-century-boys-19",
      "id": "3216734",
      "cover_url": "https://images-na.ssl-images-amazon.com/images/S/compressed.photo.goodreads.com/books/1207817701i/3183874.jpg",
      "authors": [
        "Naoki Urasawa"
      ],
      "genres": [
        "manga",
        "comics",
        "science-fiction",
        "mystery",
        "seinen",
        "graphic-novels",
        "fiction"
      ],
      "rating": 4.38,
      "ratings": 1997,
      "reviews": 62
    },
    {
      "title": "Gantz /11",
      "url": "https://www.goodreads.com/book/show/555593.Gantz_11",
      "id": "14157317",
      "cover_url": "https://images-na.ssl-images-amazon.com/images/S/compressed.photo.goodreads.com/books/1332695460i/555593.jpg",
      "authors": [
        "Hiroya Oku"
      ],
      "genres": [
        "manga",
        "science-fiction",
        "seinen",
        "horror",
        "action",
        "graphic-novels",
        "fiction"
      ],
      "rating": 4.08,
      "ratings": 1985,
      "reviews": 57
    },
    {
      "title": "20th Century Boys, Tome 20",
      "url": "https://www.goodreads.com/book/show/3031568-20th-century-boys-tome-20",
      "id": "3062163",
      "cover_url": "https://images-na.ssl-images-amazon.com/images/S/compressed.photo.goodreads.com/books/1344504757i/3031568.jpg",
      "authors": [
        "Naoki Urasawa"
      ],
      "genres": [
        "manga",
        "comics",
        "science-fiction",
        "mystery",
        "seinen",
        "graphic-novels",
        "fiction"
      ],
      "rating": 4.41,
      "ratings": 1982,
      "reviews": 62
    },
    {
      "title": "20th Century Boys 18",
      "url": "https://www.goodreads.com/book/show/1725516.20th_Century_Boys_18",
      "id": "2260564",
      "cover_url": "https://images-na.ssl-images-amazon.com/images/S/compressed.photo.goodreads.com/books/1344501288i/1725516.jpg",
      "authors": [
        "Naoki Urasawa"
      ],
      "genres": [
        "manga",
        "comics",
        "science-fiction",
        "mystery",
        "seinen",
        "graphic-novels",
        "fiction"
      ],
      "rating": 4.4,
      "ratings": 1982,
      "reviews": 76
    },
    {
      "title": "Vagabond, Volume 20",
      "url": "https://www.goodreads.com/book/show/13557.Vagabond_Volume_20",
      "id": "15697",
      "cover_url": "https://images-na.ssl-images-amazon.com/images/S/compressed.photo.goodreads.com/books/1348412979i/13557.jpg",
      "authors": [
        "Takehiko Inoue"
      ],
      "genres": [
        "manga",
        "comics",
        "historical-fiction",
        "seinen",
        "historical",
        "fiction",
        "comics-manga"
      ],
      "rating": 4.6,
      "ratings": 1981,
      "reviews": 65
    },
    {
      "title": "Solanin, Tome 1",
      "url": "https://www.goodreads.com/book/show/6321259-solanin-tome-1",
      "id": "6506664",
      "cover_url": "https://images-na.ssl-images-amazon.com/images/S/compressed.photo.goodreads.com/books/1579029593i/6321259.jpg",
      "authors": [
        "Inio Asano"
      ],
      "genres": [
        "manga",
        "comics",
        "graphic-novels",
        "slice-of-life",
        "japan",
        "seinen",
        "fiction"
      ],
      "rating": 4.11,
      "ratings": 1972,
      "reviews": 205
    },
    {
      "title": "20th Century Boys 17",
      "url": "https://www.goodreads.com/book/show/1725522.20th_Century_Boys_17",
      "id": "2200275",
      "cover_url": "https://images-na.ssl-images-amazon.com/images/S/compressed.photo.goodreads.com/books/1344500318i/1725522.jpg",
      "authors": [
        "Naoki Urasawa"
      ],
      "genres": [
        "manga",
        "comics",
        "science-fiction",
        "mystery",
        "graphic-novels",
        "seinen",
        "fiction"
      ],
      "rating": 4.4,
      "ratings": 1970,
      "reviews": 76
    },
    {
      "title": "20th Century Boys, Tome 22",
      "url": "https://www.goodreads.com/book/show/3031554-20th-century-boys-tome-22",
      "id": "3062149",
      "cover_url": "https://images-na.ssl-images-amazon.com/images/S/compressed.photo.goodreads.com/books/1344506318i/3031554.jpg",
      "authors": [
        "Naoki Urasawa"
      ],
      "genres": [
        "manga",
        "comics",
        "science-fiction",
        "mystery",
        "seinen",
        "graphic-novels",
        "fiction"
      ],
      "rating": 4.27,
      "ratings": 1964,
      "reviews": 135
    },
    {
      "title": "My Dress-Up Darling, Vol. 8",
      "url": "https://www.goodreads.com/book/show/61405936-my-dress-up-darling-vol-8",
      "id": "94248042",
      "cover_url": "https://images-na.ssl-images-amazon.com/images/S/compressed.photo.goodreads.com/books/1682569127i/61405936.jpg",
      "authors": [
        "Shinichi Fukuda"
      ],
      "genres": [
        "manga",
        "romance",
        "slice-of-life",
        "seinen",
        "graphic-novels",
        "fiction",
        "comics"
      ],
      "rating": 4.47,
      "ratings": 1958,
      "reviews": 108
    },
    {
      "title": "20th Century Boys: The Perfect Edition, Vol. 6",
      "url": "https://www.goodreads.com/book/show/43909421-20th-century-boys",
      "id": "57172252",
      "cover_url": "https://images-na.ssl-images-amazon.com/images/S/compressed.photo.goodreads.com/books/1566731730i/43909421.jpg",
      "authors": [
        "Naoki Urasawa"
      ],
      "genres": [
        "manga",
        "comics",
        "seinen",
        "graphic-novels",
        "comics-manga",
        "science-fiction",
        "mystery"
      ],
      "rating": 4.62,
      "ratings": 1956,
      "reviews": 96
    },
    {
      "title": "Kaguya-sama: Love Is War, Vol. 5",
      "url": "https://www.goodreads.com/book/show/33023060-kaguya-sama",
      "id": "53677290",
      "cover_url": "https://images-na.ssl-images-amazon.com/images/S/compressed.photo.goodreads.com/books/1541421693i/33023060.jpg",
      "authors": [
        "Aka Akasaka"
      ],
      "genres": [
        "manga",
        "romance",
        "comedy",
        "humor",
        "seinen",
        "young-adult",
        "fiction"
      ],
      "rating": 4.44,
      "ratings": 1944,
      "reviews": 99
    },
    {
      "title": "Dorohedoro, Vol. 6",
      "url": "https://www.goodreads.com/book/show/12857371-dorohedoro-vol-6",
      "id": "18009038",
      "cover_url": "https://images-na.ssl-images-amazon.com/images/S/compressed.photo.goodreads.com/books/1348058072i/12857371.jpg",
      "authors": [
        "Q. Hayashida"
      ],
      "genres": [
        "manga",
        "horror",
        "fantasy",
        "comics",
        "seinen",
        "fiction",
        "comics-manga"
      ],
      "rating": 4.49,
      "ratings": 1936,
      "reviews": 88
    },
    {
      "title": "Gantz /9",
      "url": "https://www.goodreads.com/book/show/1201650.Gantz_9",
      "id": "10124712",
      "cover_url": "https://images-na.ssl-images-amazon.com/images/S/compressed.photo.goodreads.com/books/1264195030i/1201650.jpg",
      "authors": [
        "Hiroya Oku"
      ],
      "genres": [
        "manga",
        "comics",
        "horror",
        "seinen",
        "science-fiction",
        "action",
        "fiction"
      ],
      "rating": 4.1,
      "ratings": 1936,
      "reviews": 62
    },
    {
      "title": "Vagabond, Volume 21",
      "url": "https://www.goodreads.com/book/show/251913.Vagabond_Volume_21",
      "id": "244105",
      "cover_url": "https://images-na.ssl-images-amazon.com/images/S/compressed.photo.goodreads.com/books/1573413266i/251913.jpg",
      "authors": [
        "Takehiko Inoue"
      ],
      "genres": [
        "manga",
        "historical-fiction",
        "seinen",
        "comics-manga",
        "fiction",
        "historical",
        "graphic-novels"
      ],
      "rating": 4.66,
      "ratings": 1920,
      "reviews": 51
    },
    {
      "title": "Battle Royale, Vol. 05",
      "url": "https://www.goodreads.com/book/show/266593.Battle_Royale_Vol_05",
      "id": "258476",
      "cover_url": "https://images-na.ssl-images-amazon.com/images/S/compressed.photo.goodreads.com/books/1354587118i/266593.jpg",
      "authors": [
        "Koushun Takami"
      ],
      "genres": [
        "manga",
        "comics",
        "graphic-novels",
        "horror",
        "seinen",
        "dystopia",
        "fiction"
      ],
      "rating": 4.12,
      "ratings": 1897,
      "reviews": 62
    },
    {
      "title": "Gantz/7",
      "url": "https://www.goodreads.com/book/show/2049300.Gantz_7",
      "id": "2054236",
      "cover_url": "https://images-na.ssl-images-amazon.com/images/S/compressed.photo.goodreads.com/books/1572451122i/2049300.jpg",
      "authors": [
        "Hiroya Oku"
      ],
      "genres": [
        "science-fiction",
        "horror",
        "seinen",
        "manga",
        "action",
        "graphic-novels",
        "comics"
      ],
      "rating": 4.12,
      "ratings": 1896,
      "reviews": 72
    },
    {
      "title": "Gantz/6",
      "url": "https://www.goodreads.com/book/show/2049267.Gantz_6",
      "id": "2054203",
      "cover_url": "https://images-na.ssl-images-amazon.com/images/S/compressed.photo.goodreads.com/books/1332179780i/2049267.jpg",
      "authors": [
        "Hiroya Oku"
      ],
      "genres": [
        "manga",
        "comics",
        "science-fiction",
        "horror",
        "seinen",
        "action",
        "fiction"
      ],
      "rating": 4.03,
      "ratings": 1892,
      "reviews": 65
    },
    {
      "title": "20th Century Boys, Tome 21",
      "url": "https://www.goodreads.com/book/show/3031567-20th-century-boys-tome-21",
      "id": "3062162",
      "cover_url": "https://images-na.ssl-images-amazon.com/images/S/compressed.photo.goodreads.com/books/1344505563i/3031567.jpg",
      "authors": [
        "Naoki Urasawa"
      ],
      "genres": [
        "comics",
        "science-fiction",
        "mystery",
        "seinen",
        "graphic-novels",
        "fiction",
        "manga"
      ],
      "rating": 4.36,
      "ratings": 1881,
      "reviews": 62
    },
    {
      "title": "Vagabond, Volume 22",
      "url": "https://www.goodreads.com/book/show/251909.Vagabond_Volume_22",
      "id": "244101",
      "cover_url": "https://images-na.ssl-images-amazon.com/images/S/compressed.photo.goodreads.com/books/1348804514i/251909.jpg",
      "authors": [
        "Takehiko Inoue"
      ],
      "genres": [
        "manga",
        "comics",
        "historical-fiction",
        "seinen",
        "comics-manga",
        "historical",
        "fiction"
      ],
      "rating": 4.67,
      "ratings": 1858,
      "reviews": 55
    },
    {
      "title": "Dorohedoro, Vol. 7",
      "url": "https://www.goodreads.com/book/show/13259248-dorohedoro-vol-7",
      "id": "6975439",
      "cover_url": "https://images-na.ssl-images-amazon.com/images/S/compressed.photo.goodreads.com/books/1344397916i/13259248.jpg",
      "authors": [
        "Q. Hayashida"
      ],
      "genres": [
        "manga",
        "fantasy",
        "horror",
        "comics",
        "seinen",
        "fiction",
        "graphic-novels"
      ],
      "rating": 4.5,
      "ratings": 1858,
      "reviews": 84
    },
    {
      "title": "Vinland Saga, Tome 3",
      "url": "https://www.goodreads.com/book/show/7860813-vinland-saga-tome-3",
      "id": "11009230",
      "cover_url": "https://images-na.ssl-images-amazon.com/images/S/compressed.photo.goodreads.com/books/1350286353i/7860813.jpg",
      "authors": [
        "Makoto Yukimura"
      ],
      "genres": [
        "manga",
        "historical-fiction",
        "comics",
        "seinen",
        "historical",
        "fiction",
        "graphic-novels"
      ],
      "rating": 4.36,
      "ratings": 1844,
      "reviews": 77
    },
    {
      "title": "Neon Genesis Evangelion, Vol. 11",
      "url": "https://www.goodreads.com/book/show/3043270-neon-genesis-evangelion-vol-11",
      "id": "3073915",
      "cover_url": "https://images-na.ssl-images-amazon.com/images/S/compressed.photo.goodreads.com/books/1347312445i/3043270.jpg",
      "authors": [
        "Yoshiyuki Sadamoto"
      ],
      "genres": [
        "manga",
        "comics",
        "science-fiction",
        "seinen",
        "graphic-novels",
        "young-adult",
        "action"
      ],
      "rating": 4.34,
      "ratings": 1838,
      "reviews": 77
    }
  ]
}
