{
  "books": [
    {
      "title": "The Most Defining Moments in Black History According to Dick Gregory",
      "url": "https://www.goodreads.com/book/show/33640240-the-most-defining-moments-in-black-history-according-to-dick-gregory",
      "id": "54491276",
      "cover_url": "https://images-na.ssl-images-amazon.com/images/S/compressed.photo.goodreads.com/books/1503311095i/33640240.jpg",
      "authors": [
        "Dick Gregory"
      ],
      "genres": [
        "history",
        "non-fiction",
        "african-american",
        "humor",
        "race",
        "audiobook",
        "politics"
      ],
      "rating": 4.04,
      "ratings": 1635,
      "reviews": 263
    },
    {
      "title": "Finally Famous",
      "url": "https://www.goodreads.com/book/show/199212167-finally-famous",
      "id": "203100845",
      "cover_url": "https://images-na.ssl-images-amazon.com/images/S/compressed.photo.goodreads.com/books/1695900608i/199212167.jpg",
      "authors": [
        "Ladii Nesha"
      ],
      "genres": [
        "romance",
        "african-american",
        "african-american-romance"
      ],
      "rating": 4.77,
      "ratings": 1629,
      "reviews": 242
    },
    {
      "title": "A Moment of Silence: Midnight III",
      "url": "https://www.goodreads.com/book/show/25111077-a-moment-of-silence",
      "id": "44804784",
      "cover_url": "https://images-na.ssl-images-amazon.com/images/S/compressed.photo.goodreads.com/books/1447137972i/25111077.jpg",
      "authors": [
        "Sister Souljah"
      ],
      "genres": [
        "fiction",
        "urban",
        "romance",
        "african-american"
      ],
      "rating": 4.32,
      "ratings": 1627,
      "reviews": 181
    },
    {
      "title": "Oops!",
      "url": "https://www.goodreads.com/book/show/53307187-oops",
      "id": "81484373",
      "cover_url": "https://images-na.ssl-images-amazon.com/images/S/compressed.photo.goodreads.com/books/1588347493i/53307187.jpg",
      "authors": [
        "Alexandra Warren"
      ],
      "genres": [
        "romance",
        "contemporary-romance",
        "contemporary",
        "adult",
        "african-american-romance",
        "african-american",
        "fiction"
      ],
      "rating": 4.43,
      "ratings": 1625,
      "reviews": 288
    },
    {
      "title": "Divided Soul: The Life Of Marvin Gaye",
      "url": "https://www.goodreads.com/book/show/385795.Divided_Soul",
      "id": "375493",
      "cover_url": "https://images-na.ssl-images-amazon.com/images/S/compressed.photo.goodreads.com/books/1347639348i/385795.jpg",
      "authors": [
        "David Ritz"
      ],
      "genres": [
        "music",
        "biography",
        "non-fiction",
        "history",
        "memoir",
        "african-american",
        "biography-memoir"
      ],
      "rating": 4.11,
      "ratings": 1620,
      "reviews": 151
    },
    {
      "title": "Forged in Desire",
      "url": "https://www.goodreads.com/book/show/29095429-forged-in-desire",
      "id": "51168422",
      "cover_url": "https://images-na.ssl-images-amazon.com/images/S/compressed.photo.goodreads.com/books/1475781104i/29095429.jpg",
      "authors": [
        "Brenda Jackson"
      ],
      "genres": [
        "romance",
        "romantic-suspense",
        "contemporary",
        "contemporary-romance",
        "suspense",
        "fiction",
        "african-american"
      ],
      "rating": 4.08,
      "ratings": 1618,
      "reviews": 228
    },
    {
      "title": "Love Burn",
      "url": "https://www.goodreads.com/book/show/24990539-love-burn",
      "id": "44658911",
      "cover_url": "https://images-na.ssl-images-amazon.com/images/S/compressed.photo.goodreads.com/books/1424569655i/24990539.jpg",
      "authors": [
        "Ashley Antoinette"
      ],
      "genres": [
        "urban",
        "african-american"
      ],
      "rating": 4.45,
      "ratings": 1617,
      "reviews": 182
    },
    {
      "title": "Lady J",
      "url": "https://www.goodreads.com/book/show/2821648-lady-j",
      "id": "2847741",
      "cover_url": "https://images-na.ssl-images-amazon.com/images/S/compressed.photo.goodreads.com/books/1348334475i/2821648.jpg",
      "authors": [
        "L. Divine"
      ],
      "genres": [
        "young-adult",
        "drama",
        "african-american",
        "urban",
        "contemporary",
        "teen",
        "realistic-fiction"
      ],
      "rating": 4.63,
      "ratings": 1616,
      "reviews": 55
    },
    {
      "title": "Don't Touch My Hair!",
      "url": "https://www.goodreads.com/book/show/38929947-don-t-touch-my-hair",
      "id": "60510981",
      "cover_url": "https://images-na.ssl-images-amazon.com/images/S/compressed.photo.goodreads.com/books/1523311664i/38929947.jpg",
      "authors": [
        "Sharee Miller"
      ],
      "genres": [
        "picture-books",
        "childrens",
        "african-american",
        "fiction",
        "storytime",
        "cultural",
        "race"
      ],
      "rating": 4.41,
      "ratings": 1616,
      "reviews": 326
    },
    {
      "title": "Voyage of the Sable Venus and Other Poems",
      "url": "https://www.goodreads.com/book/show/25176023-voyage-of-the-sable-venus-and-other-poems",
      "id": "44882024",
      "cover_url": "https://images-na.ssl-images-amazon.com/images/S/compressed.photo.goodreads.com/books/1442410361i/25176023.jpg",
      "authors": [
        "Robin Coste Lewis"
      ],
      "genres": [
        "poetry",
        "race",
        "feminism",
        "african-american",
        "non-fiction",
        "womens",
        "art"
      ],
      "rating": 4.3,
      "ratings": 1612,
      "reviews": 235
    },
    {
      "title": "Love Lost",
      "url": "https://www.goodreads.com/book/show/17913556-love-lost",
      "id": "25104551",
      "cover_url": "https://images-na.ssl-images-amazon.com/images/S/compressed.photo.goodreads.com/books/1368465224i/17913556.jpg",
      "authors": [
        "Love Belvin"
      ],
      "genres": [
        "romance",
        "african-american-romance",
        "contemporary-romance",
        "fiction",
        "drama",
        "erotica",
        "african-american"
      ],
      "rating": 4.5,
      "ratings": 1608,
      "reviews": 235
    },
    {
      "title": "Going Down Home with Daddy",
      "url": "https://www.goodreads.com/book/show/40685673-going-down-home-with-daddy",
      "id": "63269160",
      "cover_url": "https://images-na.ssl-images-amazon.com/images/S/compressed.photo.goodreads.com/books/1544465152i/40685673.jpg",
      "authors": [
        "Kelly Starling Lyons"
      ],
      "genres": [
        "picture-books",
        "family",
        "childrens",
        "african-american",
        "realistic-fiction",
        "fiction",
        "cultural"
      ],
      "rating": 4.24,
      "ratings": 1603,
      "reviews": 406
    },
    {
      "title": "I Could Fall in Love",
      "url": "https://www.goodreads.com/book/show/60176583-i-could-fall-in-love",
      "id": "94911035",
      "cover_url": "https://images-na.ssl-images-amazon.com/images/S/compressed.photo.goodreads.com/books/1642795162i/60176583.jpg",
      "authors": [
        "Kimberly   Brown"
      ],
      "genres": [
        "romance",
        "african-american-romance",
        "novella",
        "contemporary",
        "african-american"
      ],
      "rating": 4.6,
      "ratings": 1602,
      "reviews": 251
    },
    {
      "title": "When the Beat Was Born: DJ Kool Herc and the Creation of Hip Hop",
      "url": "https://www.goodreads.com/book/show/16075954-when-the-beat-was-born",
      "id": "21871411",
      "cover_url": "https://images-na.ssl-images-amazon.com/images/S/compressed.photo.goodreads.com/books/1377935662i/16075954.jpg",
      "authors": [
        "Laban Carrick Hill"
      ],
      "genres": [
        "picture-books",
        "biography",
        "music",
        "non-fiction",
        "childrens",
        "history",
        "african-american"
      ],
      "rating": 4.01,
      "ratings": 1600,
      "reviews": 254
    },
    {
      "title": "The Stolen Daughter",
      "url": "https://www.goodreads.com/book/show/51651028-the-stolen-daughter",
      "id": "72581206",
      "cover_url": "https://images-na.ssl-images-amazon.com/images/S/compressed.photo.goodreads.com/books/1706030921i/51651028.jpg",
      "authors": [
        "ReShonda Tate Billingsley"
      ],
      "genres": [
        "fiction",
        "contemporary",
        "african-american",
        "audiobook",
        "christian-fiction",
        "adult-fiction",
        "christian"
      ],
      "rating": 4.17,
      "ratings": 1591,
      "reviews": 230
    },
    {
      "title": "Real American: A Memoir",
      "url": "https://www.goodreads.com/book/show/33898879-real-american",
      "id": "54863812",
      "cover_url": "https://images-na.ssl-images-amazon.com/images/S/compressed.photo.goodreads.com/books/1494367658i/33898879.jpg",
      "authors": [
        "Julie Lythcott-Haims"
      ],
      "genres": [
        "memoir",
        "non-fiction",
        "biography",
        "race",
        "social-justice",
        "african-american",
        "audiobook"
      ],
      "rating": 4.43,
      "ratings": 1586,
      "reviews": 241
    },
    {
      "title": "Seize the Time: The Story of the Black Panther Party and Huey P. Newton",
      "url": "https://www.goodreads.com/book/show/371464.Seize_the_Time",
      "id": "361424",
      "cover_url": "https://images-na.ssl-images-amazon.com/images/S/compressed.photo.goodreads.com/books/1388207480i/371464.jpg",
      "authors": [
        "Bobby Seale"
      ],
      "genres": [
        "history",
        "non-fiction",
        "politics",
        "race",
        "african-american",
        "biography",
        "memoir"
      ],
      "rating": 4.34,
      "ratings": 1586,
      "reviews": 67
    },
    {
      "title": "Fifth Born",
      "url": "https://www.goodreads.com/book/show/594776.Fifth_Born",
      "id": "581491",
      "cover_url": "https://images-na.ssl-images-amazon.com/images/S/compressed.photo.goodreads.com/books/1388182725i/594776.jpg",
      "authors": [
        "Zelda Lockhart"
      ],
      "genres": [
        "fiction",
        "historical-fiction",
        "african-american",
        "abuse",
        "race",
        "realistic-fiction",
        "southern"
      ],
      "rating": 4.25,
      "ratings": 1585,
      "reviews": 139
    },
    {
      "title": "Walking in My Joy: In These Streets",
      "url": "https://www.goodreads.com/book/show/59573746-walking-in-my-joy",
      "id": "93819668",
      "cover_url": "https://images-na.ssl-images-amazon.com/images/S/compressed.photo.goodreads.com/books/1644884163i/59573746.jpg",
      "authors": [
        "Jenifer Lewis"
      ],
      "genres": [
        "memoir",
        "non-fiction",
        "audiobook",
        "mental-health",
        "biography",
        "autobiography",
        "african-american"
      ],
      "rating": 4.25,
      "ratings": 1576,
      "reviews": 243
    },
    {
      "title": "Becoming Ms. Burton: From Prison to Recovery to Leading the Fight for Incarcerated Women",
      "url": "https://www.goodreads.com/book/show/31213015-becoming-ms-burton",
      "id": "51867609",
      "cover_url": "https://images-na.ssl-images-amazon.com/images/S/compressed.photo.goodreads.com/books/1491957579i/31213015.jpg",
      "authors": [
        "Susan Burton"
      ],
      "genres": [
        "non-fiction",
        "memoir",
        "social-justice",
        "biography",
        "feminism",
        "african-american",
        "sociology"
      ],
      "rating": 4.6,
      "ratings": 1576,
      "reviews": 223
    },
    {
      "title": "My Life, My Love, My Legacy",
      "url": "https://www.goodreads.com/book/show/30199434-my-life-my-love-my-legacy",
      "id": "50650497",
      "cover_url": "https://images-na.ssl-images-amazon.com/images/S/compressed.photo.goodreads.com/books/1483091048i/30199434.jpg",
      "authors": [
        "Coretta Scott King"
      ],
      "genres": [
        "non-fiction",
        "memoir",
        "biography",
        "history",
        "audiobook",
        "african-american",
        "autobiography"
      ],
      "rating": 4.21,
      "ratings": 1575,
      "reviews": 290
    },
    {
      "title": "Gem of the Ocean",
      "url": "https://www.goodreads.com/book/show/764325.Gem_of_the_Ocean",
      "id": "268788",
      "cover_url": "https://images-na.ssl-images-amazon.com/images/S/compressed.photo.goodreads.com/books/1354209853i/764325.jpg",
      "authors": [
        "August Wilson"
      ],
      "genres": [
        "plays",
        "drama",
        "fiction",
        "historical-fiction",
        "african-american",
        "theatre",
        "classics"
      ],
      "rating": 4.13,
      "ratings": 1575,
      "reviews": 160
    },
    {
      "title": "The Black Dahlia",
      "url": "https://www.goodreads.com/book/show/13260540-the-black-dahlia",
      "id": "18462045",
      "cover_url": "https://images-na.ssl-images-amazon.com/images/S/compressed.photo.goodreads.com/books/1406525831i/13260540.jpg",
      "authors": [
        "Ashley Antoinette"
      ],
      "genres": [
        "urban",
        "african-american",
        "adult",
        "romance",
        "audiobook",
        "african-american-literature"
      ],
      "rating": 4.58,
      "ratings": 1570,
      "reviews": 128
    },
    {
      "title": "The Race Beat: The Press, the Civil Rights Struggle, and the Awakening of a Nation",
      "url": "https://www.goodreads.com/book/show/108422.The_Race_Beat",
      "id": "104482",
      "cover_url": "https://images-na.ssl-images-amazon.com/images/S/compressed.photo.goodreads.com/books/1320445224i/108422.jpg",
      "authors": [
        "Gene Roberts"
      ],
      "genres": [
        "history",
        "non-fiction",
        "journalism",
        "race",
        "american-history",
        "politics",
        "african-american"
      ],
      "rating": 4.21,
      "ratings": 1569,
      "reviews": 155
    },
    {
      "title": "Belle and the Beau",
      "url": "https://www.goodreads.com/book/show/402056.Belle_and_the_Beau",
      "id": "391454",
      "cover_url": "https://images-na.ssl-images-amazon.com/images/S/compressed.photo.goodreads.com/books/1387668944i/402056.jpg",
      "authors": [
        "Beverly Jenkins"
      ],
      "genres": [
        "romance",
        "historical-fiction",
        "young-adult",
        "historical-romance",
        "historical",
        "fiction",
        "african-american"
      ],
      "rating": 4.25,
      "ratings": 1564,
      "reviews": 140
    },
    {
      "title": "Black Friday",
      "url": "https://www.goodreads.com/book/show/9027087-black-friday",
      "id": "13904737",
      "cover_url": "https://images-na.ssl-images-amazon.com/images/S/compressed.photo.goodreads.com/books/1348196985i/9027087.jpg",
      "authors": [
        "Ashley Antoinette"
      ],
      "genres": [
        "african-american",
        "urban"
      ],
      "rating": 4.45,
      "ratings": 1563,
      "reviews": 128
    },
    {
      "title": "Pretty Ugly",
      "url": "https://www.goodreads.com/book/show/9964936-pretty-ugly",
      "id": "14858926",
      "cover_url": "https://images-na.ssl-images-amazon.com/images/S/compressed.photo.goodreads.com/books/1410561244i/9964936.jpg",
      "authors": [
        "Karyn Langhorne Folan"
      ],
      "genres": [
        "realistic-fiction",
        "drama",
        "young-adult",
        "school",
        "contemporary",
        "african-american"
      ],
      "rating": 4.43,
      "ratings": 1562,
      "reviews": 109
    },
    {
      "title": "Midnight Without a Moon",
      "url": "https://www.goodreads.com/book/show/28114583-midnight-without-a-moon",
      "id": "48123874",
      "cover_url": "https://images-na.ssl-images-amazon.com/images/S/compressed.photo.goodreads.com/books/1454608210i/28114583.jpg",
      "authors": [
        "Linda Williams Jackson"
      ],
      "genres": [
        "historical-fiction",
        "middle-grade",
        "young-adult",
        "fiction",
        "historical",
        "african-american",
        "childrens"
      ],
      "rating": 4.17,
      "ratings": 1558,
      "reviews": 347
    },
    {
      "title": "The People Could Fly: American Black Folktales",
      "url": "https://www.goodreads.com/book/show/292250.The_People_Could_Fly",
      "id": "2451299",
      "cover_url": "https://images-na.ssl-images-amazon.com/images/S/compressed.photo.goodreads.com/books/1173462229i/292250.jpg",
      "authors": [
        "Virginia Hamilton"
      ],
      "genres": [
        "short-stories",
        "folklore",
        "childrens",
        "fiction",
        "african-american",
        "picture-books",
        "folk-tales"
      ],
      "rating": 4.29,
      "ratings": 1553,
      "reviews": 218
    },
    {
      "title": "He's Just a Friend",
      "url": "https://www.goodreads.com/book/show/164350.He_s_Just_a_Friend",
      "id": "158667",
      "cover_url": "https://images-na.ssl-images-amazon.com/images/S/compressed.photo.goodreads.com/books/1347282160i/164350.jpg",
      "authors": [
        "Mary B. Morrison"
      ],
      "genres": [
        "romance",
        "adult-fiction",
        "african-american"
      ],
      "rating": 4.31,
      "ratings": 1547,
      "reviews": 38
    },
    {
      "title": "Thrall",
      "url": "https://www.goodreads.com/book/show/13429607-thrall",
      "id": "18920329",
      "cover_url": "https://images-na.ssl-images-amazon.com/images/S/compressed.photo.goodreads.com/books/1351404107i/13429607.jpg",
      "authors": [
        "Natasha Trethewey"
      ],
      "genres": [
        "poetry",
        "history",
        "race",
        "african-american",
        "non-fiction",
        "african-american-literature",
        "contemporary"
      ],
      "rating": 4.14,
      "ratings": 1543,
      "reviews": 215
    },
    {
      "title": "With Your Permission",
      "url": "https://www.goodreads.com/book/show/43604138-with-your-permission",
      "id": "67845569",
      "cover_url": "https://images-na.ssl-images-amazon.com/images/S/compressed.photo.goodreads.com/books/1547772563i/43604138.jpg",
      "authors": [
        "Stephanie Nicole Norris"
      ],
      "genres": [
        "romance",
        "audiobook",
        "african-american-romance",
        "contemporary",
        "adult",
        "african-american",
        "novella"
      ],
      "rating": 4.62,
      "ratings": 1539,
      "reviews": 283
    },
    {
      "title": "The Devil You Know: A Black Power Manifesto",
      "url": "https://www.goodreads.com/book/show/54496101-the-devil-you-know",
      "id": "80641391",
      "cover_url": "https://images-na.ssl-images-amazon.com/images/S/compressed.photo.goodreads.com/books/1602563412i/54496101.jpg",
      "authors": [
        "Charles M. Blow"
      ],
      "genres": [
        "non-fiction",
        "race",
        "politics",
        "history",
        "social-justice",
        "african-american",
        "anti-racist"
      ],
      "rating": 4.31,
      "ratings": 1530,
      "reviews": 223
    },
    {
      "title": "One Last Word: Wisdom from the Harlem Renaissance",
      "url": "https://www.goodreads.com/book/show/30039046-one-last-word",
      "id": "50443236",
      "cover_url": "https://images-na.ssl-images-amazon.com/images/S/compressed.photo.goodreads.com/books/1478284810i/30039046.jpg",
      "authors": [
        "Nikki Grimes"
      ],
      "genres": [
        "poetry",
        "middle-grade",
        "young-adult",
        "african-american",
        "childrens",
        "juvenile",
        "cultural"
      ],
      "rating": 4.31,
      "ratings": 1527,
      "reviews": 368
    },
    {
      "title": "Sleeping With the Dictionary",
      "url": "https://www.goodreads.com/book/show/95874.Sleeping_With_the_Dictionary",
      "id": "1030303",
      "cover_url": "https://images-na.ssl-images-amazon.com/images/S/compressed.photo.goodreads.com/books/1392245426i/95874.jpg",
      "authors": [
        "Harryette Mullen"
      ],
      "genres": [
        "poetry",
        "african-american",
        "college",
        "language",
        "non-fiction",
        "the-united-states-of-america",
        "united-states"
      ],
      "rating": 4,
      "ratings": 1525,
      "reviews": 108
    },
    {
      "title": "Black Is a Rainbow Color",
      "url": "https://www.goodreads.com/book/show/44280848-black-is-a-rainbow-color",
      "id": "68794404",
      "cover_url": "https://images-na.ssl-images-amazon.com/images/S/compressed.photo.goodreads.com/books/1570938578i/44280848.jpg",
      "authors": [
        "Angela Joy"
      ],
      "genres": [
        "picture-books",
        "poetry",
        "african-american",
        "childrens",
        "history",
        "social-justice",
        "storytime"
      ],
      "rating": 4.53,
      "ratings": 1522,
      "reviews": 356
    },
    {
      "title": "Blood Dazzler",
      "url": "https://www.goodreads.com/book/show/3348584-blood-dazzler",
      "id": "3386986",
      "cover_url": "https://images-na.ssl-images-amazon.com/images/S/compressed.photo.goodreads.com/books/1354209745i/3348584.jpg",
      "authors": [
        "Patricia Smith"
      ],
      "genres": [
        "poetry",
        "history",
        "african-american",
        "non-fiction",
        "race",
        "school",
        "science"
      ],
      "rating": 4.42,
      "ratings": 1520,
      "reviews": 144
    },
    {
      "title": "Liam",
      "url": "https://www.goodreads.com/book/show/79248494-liam",
      "id": "104342518",
      "cover_url": "https://images-na.ssl-images-amazon.com/images/S/compressed.photo.goodreads.com/books/1673986168i/79248494.jpg",
      "authors": [
        "Grey Huffington"
      ],
      "genres": [
        "romance",
        "novella",
        "african-american",
        "african-american-romance",
        "contemporary"
      ],
      "rating": 4.64,
      "ratings": 1518,
      "reviews": 163
    },
    {
      "title": "Bonded with Ezra",
      "url": "https://www.goodreads.com/book/show/29911753-bonded-with-ezra",
      "id": "48077712",
      "cover_url": "https://images-na.ssl-images-amazon.com/images/S/compressed.photo.goodreads.com/books/1460584052i/29911753.jpg",
      "authors": [
        "Love Belvin"
      ],
      "genres": [
        "romance",
        "bdsm",
        "erotica",
        "african-american-romance",
        "drama",
        "fiction",
        "african-american"
      ],
      "rating": 4.79,
      "ratings": 1508,
      "reviews": 237
    },
    {
      "title": "Touch Me",
      "url": "https://www.goodreads.com/book/show/57011247-touch-me",
      "id": "87061855",
      "cover_url": "https://images-na.ssl-images-amazon.com/images/S/compressed.photo.goodreads.com/books/1612883599i/57011247.jpg",
      "authors": [
        "Alexandria  House"
      ],
      "genres": [
        "romance",
        "contemporary",
        "audiobook",
        "contemporary-romance",
        "african-american",
        "fiction",
        "african-american-romance"
      ],
      "rating": 4.47,
      "ratings": 1506,
      "reviews": 242
    },
    {
      "title": "A Lover's Vow",
      "url": "https://www.goodreads.com/book/show/23013976-a-lover-s-vow",
      "id": "42580241",
      "cover_url": "https://images-na.ssl-images-amazon.com/images/S/compressed.photo.goodreads.com/books/1424053443i/23013976.jpg",
      "authors": [
        "Brenda Jackson"
      ],
      "genres": [
        "romance",
        "contemporary",
        "african-american-romance",
        "romantic-suspense",
        "contemporary-romance",
        "suspense",
        "african-american"
      ],
      "rating": 4.51,
      "ratings": 1503,
      "reviews": 218
    },
    {
      "title": "Many Thousands Gone: The First Two Centuries of Slavery in North America",
      "url": "https://www.goodreads.com/book/show/178481.Many_Thousands_Gone",
      "id": "172421",
      "cover_url": "https://images-na.ssl-images-amazon.com/images/S/compressed.photo.goodreads.com/books/1347674189i/178481.jpg",
      "authors": [
        "Ira Berlin"
      ],
      "genres": [
        "history",
        "non-fiction",
        "american-history",
        "race",
        "african-american",
        "american",
        "social-justice"
      ],
      "rating": 4.11,
      "ratings": 1502,
      "reviews": 64
    },
    {
      "title": "The Dopeman: Memoirs of a Snitch",
      "url": "https://www.goodreads.com/book/show/7623097-the-dopeman",
      "id": "10104124",
      "cover_url": "https://images-na.ssl-images-amazon.com/images/S/compressed.photo.goodreads.com/books/1347800986i/7623097.jpg",
      "authors": [
        "JaQuavis Coleman"
      ],
      "genres": [
        "urban",
        "crime",
        "african-american"
      ],
      "rating": 4.57,
      "ratings": 1497,
      "reviews": 98
    },
    {
      "title": "A Crazy Little Thing Called Love",
      "url": "https://www.goodreads.com/book/show/23269794-a-crazy-little-thing-called-love",
      "id": "42757161",
      "cover_url": "https://images-na.ssl-images-amazon.com/images/S/compressed.photo.goodreads.com/books/1441776440i/23269794.jpg",
      "authors": [
        "Christina C. Jones"
      ],
      "genres": [
        "romance",
        "contemporary-romance",
        "african-american-romance",
        "contemporary",
        "fiction",
        "audiobook",
        "african-american"
      ],
      "rating": 4.36,
      "ratings": 1491,
      "reviews": 196
    },
    {
      "title": "The King of Kindergarten",
      "url": "https://www.goodreads.com/book/show/41854889-the-king-of-kindergarten",
      "id": "65338397",
      "cover_url": "https://images-na.ssl-images-amazon.com/images/S/compressed.photo.goodreads.com/books/1542006818i/41854889.jpg",
      "authors": [
        "Derrick Barnes"
      ],
      "genres": [
        "picture-books",
        "school",
        "childrens",
        "back-to-school",
        "storytime",
        "african-american",
        "fiction"
      ],
      "rating": 4.21,
      "ratings": 1491,
      "reviews": 274
    },
    {
      "title": "Luxe",
      "url": "https://www.goodreads.com/book/show/23848213-luxe",
      "id": "43458179",
      "cover_url": "https://images-na.ssl-images-amazon.com/images/S/compressed.photo.goodreads.com/books/1428639378i/23848213.jpg",
      "authors": [
        "Ashley Antoinette"
      ],
      "genres": [
        "urban",
        "audiobook",
        "romance",
        "african-american-romance",
        "african-american",
        "chick-lit",
        "fiction"
      ],
      "rating": 4.38,
      "ratings": 1489,
      "reviews": 203
    },
    {
      "title": "Death Before Dishonor",
      "url": "https://www.goodreads.com/book/show/339428.Death_Before_Dishonor",
      "id": "329823",
      "cover_url": "https://images-na.ssl-images-amazon.com/images/S/compressed.photo.goodreads.com/books/1427903254i/339428.jpg",
      "authors": [
        "Nikki Turner"
      ],
      "genres": [
        "fiction",
        "african-american",
        "urban"
      ],
      "rating": 4.32,
      "ratings": 1489,
      "reviews": 49
    },
    {
      "title": "The Complete Fiction of Nella Larsen: Passing, Quicksand, and The Stories",
      "url": "https://www.goodreads.com/book/show/12412.The_Complete_Fiction_of_Nella_Larsen",
      "id": "14718",
      "cover_url": "https://images-na.ssl-images-amazon.com/images/S/compressed.photo.goodreads.com/books/1427071657i/12412.jpg",
      "authors": [
        "Nella Larsen"
      ],
      "genres": [
        "fiction",
        "classics",
        "short-stories",
        "african-american",
        "race",
        "literary-fiction",
        "literature"
      ],
      "rating": 4.15,
      "ratings": 1485,
      "reviews": 148
    },
    {
      "title": "With the Might of Angels: The Diary of Dawnie Rae Johnson, Hadley, Virginia, 1954",
      "url": "https://www.goodreads.com/book/show/10382899-with-the-might-of-angels",
      "id": "15286455",
      "cover_url": "https://images-na.ssl-images-amazon.com/images/S/compressed.photo.goodreads.com/books/1327899560i/10382899.jpg",
      "authors": [
        "Andrea Davis Pinkney"
      ],
      "genres": [
        "historical-fiction",
        "middle-grade",
        "childrens",
        "young-adult",
        "historical",
        "fiction",
        "african-american"
      ],
      "rating": 4.15,
      "ratings": 1485,
      "reviews": 177
    },
    {
      "title": "I am The Rage: A Black Poetry Collection",
      "url": "https://www.goodreads.com/book/show/55829991-i-am-the-rage",
      "id": "87047878",
      "cover_url": "https://images-na.ssl-images-amazon.com/images/S/compressed.photo.goodreads.com/books/1609766560i/55829991.jpg",
      "authors": [
        "Martina McGowan"
      ],
      "genres": [
        "poetry",
        "non-fiction",
        "race",
        "social-justice",
        "contemporary",
        "feminism",
        "african-american"
      ],
      "rating": 4.35,
      "ratings": 1474,
      "reviews": 276
    }
  ]
}
