{
  "books": [
    {
      "title": "The Listener: What if you could hear what God hears?",
      "url": "https://www.goodreads.com/book/show/610556.The_Listener",
      "id": "597034",
      "cover_url": "https://images-na.ssl-images-amazon.com/images/S/compressed.photo.goodreads.com/books/1439764624i/610556.jpg",
      "authors": [
        "Terri Blackstock"
      ],
      "genres": [
        "christian-fiction",
        "fiction",
        "christian",
        "adult-fiction",
        "religion",
        "novels",
        "evangelism"
      ],
      "rating": 4.09,
      "ratings": 1015,
      "reviews": 95
    },
    {
      "title": "A Love Woven True",
      "url": "https://www.goodreads.com/book/show/360004.A_Love_Woven_True",
      "id": "1479380",
      "cover_url": "https://images-na.ssl-images-amazon.com/images/S/compressed.photo.goodreads.com/books/1348949189i/360004.jpg",
      "authors": [
        "Tracie Peterson"
      ],
      "genres": [
        "historical-fiction",
        "christian-fiction",
        "christian",
        "fiction",
        "romance",
        "historical",
        "christian-romance"
      ],
      "rating": 4.11,
      "ratings": 1015,
      "reviews": 24
    },
    {
      "title": "No More Faking Fine: Ending the Pretending",
      "url": "https://www.goodreads.com/book/show/29491886-no-more-faking-fine",
      "id": "49775954",
      "cover_url": "https://images-na.ssl-images-amazon.com/images/S/compressed.photo.goodreads.com/books/1459042650i/29491886.jpg",
      "authors": [
        "Esther Fleece Allen"
      ],
      "genres": [
        "christian",
        "non-fiction",
        "faith",
        "christian-living",
        "christian-non-fiction",
        "religion",
        "spirituality"
      ],
      "rating": 4.31,
      "ratings": 1013,
      "reviews": 133
    },
    {
      "title": "Christmas at Rose Hill Farm: An Amish Love Story",
      "url": "https://www.goodreads.com/book/show/20665232-christmas-at-rose-hill-farm",
      "id": "34212386",
      "cover_url": "https://images-na.ssl-images-amazon.com/images/S/compressed.photo.goodreads.com/books/1403178434i/20665232.jpg",
      "authors": [
        "Suzanne Woods Fisher"
      ],
      "genres": [
        "amish",
        "christmas",
        "romance",
        "fiction",
        "christian-fiction",
        "christian",
        "amish-fiction"
      ],
      "rating": 4.24,
      "ratings": 1013,
      "reviews": 158
    },
    {
      "title": "Seaside Reunion",
      "url": "https://www.goodreads.com/book/show/12377509-seaside-reunion",
      "id": "17358021",
      "cover_url": "https://images-na.ssl-images-amazon.com/images/S/compressed.photo.goodreads.com/books/1348643147i/12377509.jpg",
      "authors": [
        "Irene Hannon"
      ],
      "genres": [
        "love-inspired",
        "christian-fiction",
        "romance",
        "christian",
        "contemporary",
        "fiction",
        "christian-romance"
      ],
      "rating": 4.28,
      "ratings": 1012,
      "reviews": 79
    },
    {
      "title": "Tender Warrior: God's Intention for a Man",
      "url": "https://www.goodreads.com/book/show/1440203.Tender_Warrior",
      "id": "1430810",
      "cover_url": "https://images-na.ssl-images-amazon.com/images/S/compressed.photo.goodreads.com/books/1183611290i/1440203.jpg",
      "authors": [
        "Stuart K. Weber"
      ],
      "genres": [
        "christian",
        "christian-living",
        "faith",
        "christianity",
        "non-fiction",
        "spirituality",
        "religion"
      ],
      "rating": 4.18,
      "ratings": 1012,
      "reviews": 86
    },
    {
      "title": "Letters to an American Lady",
      "url": "https://www.goodreads.com/book/show/543544.Letters_to_an_American_Lady",
      "id": "14627964",
      "cover_url": "https://images-na.ssl-images-amazon.com/images/S/compressed.photo.goodreads.com/books/1348153772i/543544.jpg",
      "authors": [
        "C.S. Lewis"
      ],
      "genres": [
        "non-fiction",
        "christian",
        "biography",
        "christianity",
        "theology",
        "classics",
        "faith"
      ],
      "rating": 4.08,
      "ratings": 1010,
      "reviews": 121
    },
    {
      "title": "Undivided: Coming Out, Becoming Whole, and Living Free from Shame",
      "url": "https://www.goodreads.com/book/show/35068562-undivided",
      "id": "56364017",
      "cover_url": "https://images-na.ssl-images-amazon.com/images/S/compressed.photo.goodreads.com/books/1523719678i/35068562.jpg",
      "authors": [
        "Vicky Beeching"
      ],
      "genres": [
        "non-fiction",
        "lgbt",
        "memoir",
        "biography",
        "christian",
        "theology",
        "religion"
      ],
      "rating": 4.49,
      "ratings": 1010,
      "reviews": 165
    },
    {
      "title": "Legacy of Lies: The Colsons",
      "url": "https://www.goodreads.com/book/show/58808229-legacy-of-lies",
      "id": "92611296",
      "cover_url": "https://images-na.ssl-images-amazon.com/images/S/compressed.photo.goodreads.com/books/1629377717i/58808229.jpg",
      "authors": [
        "Christy Barritt"
      ],
      "genres": [
        "christian-fiction",
        "suspense",
        "mystery",
        "romance",
        "mystery-thriller",
        "christian",
        "fiction"
      ],
      "rating": 4.66,
      "ratings": 1010,
      "reviews": 92
    },
    {
      "title": "Cold Light of Day",
      "url": "https://www.goodreads.com/book/show/61140802-cold-light-of-day",
      "id": "96373051",
      "cover_url": "https://images-na.ssl-images-amazon.com/images/S/compressed.photo.goodreads.com/books/1670258990i/61140802.jpg",
      "authors": [
        "Elizabeth Goddard"
      ],
      "genres": [
        "suspense",
        "christian-fiction",
        "mystery",
        "romance",
        "romantic-suspense",
        "christian",
        "fiction"
      ],
      "rating": 4.26,
      "ratings": 1010,
      "reviews": 378
    },
    {
      "title": "The Life of Moses",
      "url": "https://www.goodreads.com/book/show/102122.The_Life_of_Moses",
      "id": "98464",
      "cover_url": "https://images-na.ssl-images-amazon.com/images/S/compressed.photo.goodreads.com/books/1347479191i/102122.jpg",
      "authors": [
        "Gregory of Nyssa"
      ],
      "genres": [
        "theology",
        "religion",
        "christianity",
        "christian",
        "spirituality",
        "non-fiction",
        "philosophy"
      ],
      "rating": 4.26,
      "ratings": 1009,
      "reviews": 113
    },
    {
      "title": "God Does His Best Work with Empty",
      "url": "https://www.goodreads.com/book/show/51979017-god-does-his-best-work-with-empty",
      "id": "76636950",
      "cover_url": "https://images-na.ssl-images-amazon.com/images/S/compressed.photo.goodreads.com/books/1585641146i/51979017.jpg",
      "authors": [
        "Nancy Guthrie"
      ],
      "genres": [
        "christian",
        "christian-living",
        "non-fiction",
        "faith",
        "christian-non-fiction",
        "theology",
        "christianity"
      ],
      "rating": 4.48,
      "ratings": 1008,
      "reviews": 157
    },
    {
      "title": "Where Treetops Glisten: Three Stories of Heartwarming Courage and Christmas Romance During World War II",
      "url": "https://www.goodreads.com/book/show/21561734-where-treetops-glisten",
      "id": "40893775",
      "cover_url": "https://images-na.ssl-images-amazon.com/images/S/compressed.photo.goodreads.com/books/1396187678i/21561734.jpg",
      "authors": [
        "Tricia Goyer"
      ],
      "genres": [
        "christmas",
        "historical-fiction",
        "christian-fiction",
        "romance",
        "fiction",
        "christian",
        "world-war-ii"
      ],
      "rating": 4.24,
      "ratings": 1008,
      "reviews": 232
    },
    {
      "title": "Dorie: The Girl Nobody Loved",
      "url": "https://www.goodreads.com/book/show/397755.Dorie",
      "id": "387218",
      "cover_url": "https://images-na.ssl-images-amazon.com/images/S/compressed.photo.goodreads.com/books/1328855196i/397755.jpg",
      "authors": [
        "Erwin W. Lutzer"
      ],
      "genres": [
        "non-fiction",
        "christian",
        "biography",
        "memoir",
        "biography-memoir",
        "inspirational",
        "autobiography"
      ],
      "rating": 4.3,
      "ratings": 1008,
      "reviews": 101
    },
    {
      "title": "The Tongue: A Creative Force",
      "url": "https://www.goodreads.com/book/show/348231.The_Tongue",
      "id": "338518",
      "cover_url": "https://images-na.ssl-images-amazon.com/images/S/compressed.photo.goodreads.com/books/1398570872i/348231.jpg",
      "authors": [
        "Charles Capps"
      ],
      "genres": [
        "christian",
        "non-fiction",
        "faith",
        "christian-living",
        "christianity",
        "religion",
        "personal-development"
      ],
      "rating": 4.47,
      "ratings": 1008,
      "reviews": 71
    },
    {
      "title": "Slightly Bad Girls of the Bible: Flawed Women Loved by a Flawless God",
      "url": "https://www.goodreads.com/book/show/230261.Slightly_Bad_Girls_of_the_Bible",
      "id": "222995",
      "cover_url": "https://images-na.ssl-images-amazon.com/images/S/compressed.photo.goodreads.com/books/1320515444i/230261.jpg",
      "authors": [
        "Liz Curtis Higgs"
      ],
      "genres": [
        "christian",
        "non-fiction",
        "religion",
        "inspirational",
        "christian-living",
        "christianity",
        "faith"
      ],
      "rating": 4.2,
      "ratings": 1008,
      "reviews": 101
    },
    {
      "title": "Preparing for Christmas: Daily Reflections for Advent",
      "url": "https://www.goodreads.com/book/show/5141884-preparing-for-christmas",
      "id": "5208784",
      "cover_url": "https://images-na.ssl-images-amazon.com/images/S/compressed.photo.goodreads.com/books/1344666207i/5141884.jpg",
      "authors": [
        "Richard Rohr"
      ],
      "genres": [
        "christmas",
        "spirituality",
        "non-fiction",
        "religion",
        "faith",
        "christianity",
        "christian"
      ],
      "rating": 4.37,
      "ratings": 1006,
      "reviews": 96
    },
    {
      "title": "Show them Jesus: Teaching the Gospel to Kids",
      "url": "https://www.goodreads.com/book/show/21565781-show-them-jesus",
      "id": "40897311",
      "cover_url": "https://images-na.ssl-images-amazon.com/images/S/compressed.photo.goodreads.com/books/1400598857i/21565781.jpg",
      "authors": [
        "Jack Klumpenhower"
      ],
      "genres": [
        "parenting",
        "christian",
        "non-fiction",
        "theology",
        "childrens",
        "christian-living",
        "christianity"
      ],
      "rating": 4.5,
      "ratings": 1006,
      "reviews": 154
    },
    {
      "title": "The First Paul: Reclaiming the Radical Visionary Behind the Church's Conservative Icon",
      "url": "https://www.goodreads.com/book/show/5705398-the-first-paul",
      "id": "5876967",
      "cover_url": "https://images-na.ssl-images-amazon.com/images/S/compressed.photo.goodreads.com/books/1442844810i/5705398.jpg",
      "authors": [
        "Marcus J. Borg"
      ],
      "genres": [
        "religion",
        "christianity",
        "theology",
        "history",
        "non-fiction",
        "spirituality",
        "christian"
      ],
      "rating": 4.1,
      "ratings": 1006,
      "reviews": 138
    },
    {
      "title": "Faithfully Different: Regaining Biblical Clarity in a Secular Culture",
      "url": "https://www.goodreads.com/book/show/57825690-faithfully-different",
      "id": "90586548",
      "cover_url": "https://images-na.ssl-images-amazon.com/images/S/compressed.photo.goodreads.com/books/1636086455i/57825690.jpg",
      "authors": [
        "Natasha Crain"
      ],
      "genres": [
        "christian",
        "non-fiction",
        "christianity",
        "theology",
        "faith",
        "christian-living",
        "religion"
      ],
      "rating": 4.62,
      "ratings": 1005,
      "reviews": 187
    },
    {
      "title": "Men of the Bible",
      "url": "https://www.goodreads.com/book/show/11088927-men-of-the-bible",
      "id": "12945289",
      "cover_url": "https://images-na.ssl-images-amazon.com/images/S/compressed.photo.goodreads.com/books/1328328507i/11088927.jpg",
      "authors": [
        "Dwight L. Moody"
      ],
      "genres": [
        "christian",
        "non-fiction",
        "religion",
        "biography",
        "christianity",
        "theology",
        "christian-non-fiction"
      ],
      "rating": 4.25,
      "ratings": 1005,
      "reviews": 70
    },
    {
      "title": "Lemons on Friday: Trusting God Through My Greatest Heartbreak",
      "url": "https://www.goodreads.com/book/show/59017456-lemons-on-friday",
      "id": "89981377",
      "cover_url": "https://images-na.ssl-images-amazon.com/images/S/compressed.photo.goodreads.com/books/1631927570i/59017456.jpg",
      "authors": [
        "Mattie Jackson Selecman"
      ],
      "genres": [
        "non-fiction",
        "christian",
        "faith",
        "memoir",
        "audiobook",
        "self-help",
        "christian-non-fiction"
      ],
      "rating": 4.47,
      "ratings": 1005,
      "reviews": 118
    },
    {
      "title": "Judge",
      "url": "https://www.goodreads.com/book/show/13617581-judge",
      "id": "19220171",
      "cover_url": "https://images-na.ssl-images-amazon.com/images/S/compressed.photo.goodreads.com/books/1335436361i/13617581.jpg",
      "authors": [
        "R.J. Larson"
      ],
      "genres": [
        "fantasy",
        "christian-fiction",
        "christian",
        "christian-fantasy",
        "fiction",
        "young-adult",
        "adventure"
      ],
      "rating": 4.41,
      "ratings": 1005,
      "reviews": 89
    },
    {
      "title": "With Autumn's Return",
      "url": "https://www.goodreads.com/book/show/18059999-with-autumn-s-return",
      "id": "23983122",
      "cover_url": "https://images-na.ssl-images-amazon.com/images/S/compressed.photo.goodreads.com/books/1372810238i/18059999.jpg",
      "authors": [
        "Amanda Cabot"
      ],
      "genres": [
        "christian-fiction",
        "romance",
        "historical-fiction",
        "christian",
        "historical",
        "fiction",
        "historical-romance"
      ],
      "rating": 4.16,
      "ratings": 1005,
      "reviews": 129
    }
  ]
}
