{
  "books": [
    {
      "title": "Band of Brothers: E Company, 506th Regiment, 101st Airborne from Normandy to Hitler's Eagle's Nest",
      "url": "https://www.goodreads.com/book/show/42389.Band_of_Brothers",
      "id": "903474",
      "cover_url": "https://images-na.ssl-images-amazon.com/images/S/compressed.photo.goodreads.com/books/1388247701i/42389.jpg",
      "authors": [
        "Stephen E. Ambrose"
      ],
      "genres": [
        "history",
        "non-fiction",
        "war",
        "military-fiction",
        "world-war-ii",
        "military-history",
        "historical"
      ],
      "rating": 4.42,
      "ratings": 124691,
      "reviews": 3559
    },
    {
      "title": "Lone Survivor: The Eyewitness Account of Operation Redwing and the Lost Heroes of SEAL Team 10",
      "url": "https://www.goodreads.com/book/show/711901.Lone_Survivor",
      "id": "1623890",
      "cover_url": "https://images-na.ssl-images-amazon.com/images/S/compressed.photo.goodreads.com/books/1344265535i/711901.jpg",
      "authors": [
        "Marcus Luttrell"
      ],
      "genres": [
        "non-fiction",
        "military-fiction",
        "history",
        "war",
        "biography",
        "memoir",
        "military-history"
      ],
      "rating": 4.34,
      "ratings": 92951,
      "reviews": 7299
    },
    {
      "title": "The Guns of August",
      "url": "https://www.goodreads.com/book/show/40779082-the-guns-of-august",
      "id": "1884932",
      "cover_url": "https://images-na.ssl-images-amazon.com/images/S/compressed.photo.goodreads.com/books/1617037342i/40779082.jpg",
      "authors": [
        "Barbara W. Tuchman"
      ],
      "genres": [
        "history",
        "non-fiction",
        "war",
        "world-war-i",
        "military-fiction",
        "military-history",
        "politics"
      ],
      "rating": 4.17,
      "ratings": 75832,
      "reviews": 3347
    },
    {
      "title": "Black Hawk Down: A Story of Modern War",
      "url": "https://www.goodreads.com/book/show/55403.Black_Hawk_Down",
      "id": "1041952",
      "cover_url": "https://images-na.ssl-images-amazon.com/images/S/compressed.photo.goodreads.com/books/1553055240i/55403.jpg",
      "authors": [
        "Mark Bowden"
      ],
      "genres": [
        "history",
        "non-fiction",
        "military-fiction",
        "war",
        "military-history",
        "africa",
        "historical"
      ],
      "rating": 4.29,
      "ratings": 64040,
      "reviews": 1909
    },
    {
      "title": "Flags of Our Fathers",
      "url": "https://www.goodreads.com/book/show/10058.Flags_of_Our_Fathers",
      "id": "2618496",
      "cover_url": "https://images-na.ssl-images-amazon.com/images/S/compressed.photo.goodreads.com/books/1386923564i/10058.jpg",
      "authors": [
        "James D. Bradley"
      ],
      "genres": [
        "history",
        "non-fiction",
        "military-fiction",
        "war",
        "world-war-ii",
        "biography",
        "military-history"
      ],
      "rating": 4.21,
      "ratings": 60291,
      "reviews": 1827
    },
    {
      "title": "No Easy Day: The Firsthand Account of the Mission That Killed Osama Bin Laden",
      "url": "https://www.goodreads.com/book/show/15814872-no-easy-day",
      "id": "21585027",
      "cover_url": "https://images-na.ssl-images-amazon.com/images/S/compressed.photo.goodreads.com/books/1345815909i/15814872.jpg",
      "authors": [
        "Mark Owen"
      ],
      "genres": [
        "non-fiction",
        "military-fiction",
        "history",
        "war",
        "biography",
        "memoir",
        "military-history"
      ],
      "rating": 4.02,
      "ratings": 53970,
      "reviews": 4138
    },
    {
      "title": "Ghost Soldiers: The Epic Account of World War II's Greatest Rescue Mission",
      "url": "https://www.goodreads.com/book/show/94799.Ghost_Soldiers",
      "id": "1484198",
      "cover_url": "https://images-na.ssl-images-amazon.com/images/S/compressed.photo.goodreads.com/books/1320454587i/94799.jpg",
      "authors": [
        "Hampton Sides"
      ],
      "genres": [
        "history",
        "non-fiction",
        "world-war-ii",
        "war",
        "military-fiction",
        "military-history",
        "american-history"
      ],
      "rating": 4.24,
      "ratings": 36429,
      "reviews": 1733
    },
    {
      "title": "Battle Cry of Freedom",
      "url": "https://www.goodreads.com/book/show/35100.Battle_Cry_of_Freedom",
      "id": "35039",
      "cover_url": "https://images-na.ssl-images-amazon.com/images/S/compressed.photo.goodreads.com/books/1388185755i/35100.jpg",
      "authors": [
        "James M. McPherson"
      ],
      "genres": [
        "history",
        "non-fiction",
        "civil-war",
        "american-history",
        "war",
        "american-civil-war",
        "military-history"
      ],
      "rating": 4.38,
      "ratings": 31097,
      "reviews": 1604
    },
    {
      "title": "We Were Soldiers Once... and Young: Ia Drang - The Battle that Changed the War in Vietnam",
      "url": "https://www.goodreads.com/book/show/42512.We_Were_Soldiers_Once_and_Young",
      "id": "41999",
      "cover_url": "https://images-na.ssl-images-amazon.com/images/S/compressed.photo.goodreads.com/books/1328912889i/42512.jpg",
      "authors": [
        "Harold G. Moore"
      ],
      "genres": [
        "history",
        "non-fiction",
        "military-fiction",
        "war",
        "military-history",
        "american-history",
        "biography"
      ],
      "rating": 4.33,
      "ratings": 30769,
      "reviews": 863
    },
    {
      "title": "D-Day, June 6, 1944: The Battle for the Normandy Beaches",
      "url": "https://www.goodreads.com/book/show/49250.D_Day_June_6_1944",
      "id": "586990",
      "cover_url": "https://images-na.ssl-images-amazon.com/images/S/compressed.photo.goodreads.com/books/1391798880i/49250.jpg",
      "authors": [
        "Stephen E. Ambrose"
      ],
      "genres": [
        "history",
        "non-fiction",
        "world-war-ii",
        "war",
        "military-history",
        "military-fiction",
        "american-history"
      ],
      "rating": 4.3,
      "ratings": 29156,
      "reviews": 876
    },
    {
      "title": "The Longest Day",
      "url": "https://www.goodreads.com/book/show/161156.The_Longest_Day",
      "id": "1413765",
      "cover_url": "https://images-na.ssl-images-amazon.com/images/S/compressed.photo.goodreads.com/books/1560902103i/161156.jpg",
      "authors": [
        "Cornelius Ryan"
      ],
      "genres": [
        "history",
        "non-fiction",
        "war",
        "world-war-ii",
        "military-fiction",
        "military-history",
        "historical"
      ],
      "rating": 4.32,
      "ratings": 24255,
      "reviews": 776
    },
    {
      "title": "Citizen Soldiers: The US Army from the Normandy Beaches to the Bulge to the Surrender of Germany",
      "url": "https://www.goodreads.com/book/show/49251.Citizen_Soldiers",
      "id": "235055",
      "cover_url": "https://images-na.ssl-images-amazon.com/images/S/compressed.photo.goodreads.com/books/1428459953i/49251.jpg",
      "authors": [
        "Stephen E. Ambrose"
      ],
      "genres": [
        "history",
        "non-fiction",
        "military-fiction",
        "world-war-ii",
        "war",
        "military-history",
        "american-history"
      ],
      "rating": 4.23,
      "ratings": 23330,
      "reviews": 527
    },
    {
      "title": "War",
      "url": "https://www.goodreads.com/book/show/7519640-war",
      "id": "9737203",
      "cover_url": "https://images-na.ssl-images-amazon.com/images/S/compressed.photo.goodreads.com/books/1344271278i/7519640.jpg",
      "authors": [
        "Sebastian Junger"
      ],
      "genres": [
        "non-fiction",
        "war",
        "history",
        "military-fiction",
        "military-history",
        "memoir",
        "psychology"
      ],
      "rating": 4.24,
      "ratings": 22639,
      "reviews": 1789
    },
    {
      "title": "In Harm's Way: The Sinking of the USS Indianapolis and the Extraordinary Story of Its Survivors",
      "url": "https://www.goodreads.com/book/show/42435.In_Harm_s_Way",
      "id": "41918",
      "cover_url": "https://images-na.ssl-images-amazon.com/images/S/compressed.photo.goodreads.com/books/1442540445i/42435.jpg",
      "authors": [
        "Doug Stanton"
      ],
      "genres": [
        "history",
        "non-fiction",
        "military-fiction",
        "world-war-ii",
        "war",
        "survival",
        "military-history"
      ],
      "rating": 4.31,
      "ratings": 22079,
      "reviews": 1302
    },
    {
      "title": "Helmet for My Pillow: From Parris Island to the Pacific",
      "url": "https://www.goodreads.com/book/show/41021227-helmet-for-my-pillow",
      "id": "1196341",
      "cover_url": "https://images-na.ssl-images-amazon.com/images/S/compressed.photo.goodreads.com/books/1533133225i/41021227.jpg",
      "authors": [
        "Robert Leckie"
      ],
      "genres": [
        "history",
        "non-fiction",
        "war",
        "military-fiction",
        "world-war-ii",
        "biography",
        "military-history"
      ],
      "rating": 4.21,
      "ratings": 21968,
      "reviews": 997
    },
    {
      "title": "Flyboys: A True Story of Courage",
      "url": "https://www.goodreads.com/book/show/202146.Flyboys",
      "id": "22829",
      "cover_url": "https://images-na.ssl-images-amazon.com/images/S/compressed.photo.goodreads.com/books/1442195112i/202146.jpg",
      "authors": [
        "James D. Bradley"
      ],
      "genres": [
        "history",
        "non-fiction",
        "world-war-ii",
        "war",
        "military-fiction",
        "military-history",
        "biography"
      ],
      "rating": 4.19,
      "ratings": 21719,
      "reviews": 1403
    },
    {
      "title": "An Army at Dawn: The War in North Africa, 1942-1943",
      "url": "https://www.goodreads.com/book/show/541920.An_Army_at_Dawn",
      "id": "1795751",
      "cover_url": "https://images-na.ssl-images-amazon.com/images/S/compressed.photo.goodreads.com/books/1440057096i/541920.jpg",
      "authors": [
        "Rick Atkinson"
      ],
      "genres": [
        "history",
        "non-fiction",
        "world-war-ii",
        "military-history",
        "war",
        "military-fiction",
        "africa"
      ],
      "rating": 4.28,
      "ratings": 20621,
      "reviews": 1226
    },
    {
      "title": "A Bridge Too Far",
      "url": "https://www.goodreads.com/book/show/539904.A_Bridge_Too_Far",
      "id": "1246930",
      "cover_url": "https://images-na.ssl-images-amazon.com/images/S/compressed.photo.goodreads.com/books/1326921431i/539904.jpg",
      "authors": [
        "Cornelius Ryan"
      ],
      "genres": [
        "history",
        "non-fiction",
        "war",
        "military-history",
        "world-war-ii",
        "military-fiction",
        "historical"
      ],
      "rating": 4.26,
      "ratings": 20619,
      "reviews": 412
    },
    {
      "title": "Dispatches",
      "url": "https://www.goodreads.com/book/show/4339.Dispatches",
      "id": "8018",
      "cover_url": "https://images-na.ssl-images-amazon.com/images/S/compressed.photo.goodreads.com/books/1343099128i/4339.jpg",
      "authors": [
        "Michael Herr"
      ],
      "genres": [
        "non-fiction",
        "history",
        "war",
        "memoir",
        "journalism",
        "military-fiction",
        "military-history"
      ],
      "rating": 4.22,
      "ratings": 19744,
      "reviews": 1305
    },
    {
      "title": "Generation Kill: Devil Dogs, Iceman, Captain America, and the New Face of American War",
      "url": "https://www.goodreads.com/book/show/543103.Generation_Kill",
      "id": "908023",
      "cover_url": "https://images-na.ssl-images-amazon.com/images/S/compressed.photo.goodreads.com/books/1441919496i/543103.jpg",
      "authors": [
        "Evan Wright"
      ],
      "genres": [
        "non-fiction",
        "military-fiction",
        "history",
        "war",
        "military-history",
        "memoir",
        "journalism"
      ],
      "rating": 4.27,
      "ratings": 18539,
      "reviews": 923
    },
    {
      "title": "SEAL Team Six: Memoirs of an Elite Navy SEAL Sniper",
      "url": "https://www.goodreads.com/book/show/9739365-seal-team-six",
      "id": "14628458",
      "cover_url": "https://images-na.ssl-images-amazon.com/images/S/compressed.photo.goodreads.com/books/1442949773i/9739365.jpg",
      "authors": [
        "Howard E. Wasdin"
      ],
      "genres": [
        "military-fiction",
        "non-fiction",
        "history",
        "biography",
        "war",
        "memoir",
        "military-history"
      ],
      "rating": 4.06,
      "ratings": 17314,
      "reviews": 972
    },
    {
      "title": "The Fall of Berlin 1945",
      "url": "https://www.goodreads.com/book/show/42661.The_Fall_of_Berlin_1945",
      "id": "300328",
      "cover_url": "https://images-na.ssl-images-amazon.com/images/S/compressed.photo.goodreads.com/books/1312049741i/42661.jpg",
      "authors": [
        "Antony Beevor"
      ],
      "genres": [
        "history",
        "non-fiction",
        "world-war-ii",
        "war",
        "military-history",
        "germany",
        "military-fiction"
      ],
      "rating": 4.29,
      "ratings": 16694,
      "reviews": 717
    },
    {
      "title": "A Rumor of War: The Classic Vietnam Memoir",
      "url": "https://www.goodreads.com/book/show/31450638-a-rumor-of-war",
      "id": "3782",
      "cover_url": "https://images-na.ssl-images-amazon.com/images/S/compressed.photo.goodreads.com/books/1499712930i/31450638.jpg",
      "authors": [
        "Philip Caputo"
      ],
      "genres": [
        "history",
        "non-fiction",
        "war",
        "military-fiction",
        "memoir",
        "military-history",
        "biography"
      ],
      "rating": 4.16,
      "ratings": 15099,
      "reviews": 720
    },
    {
      "title": "The First World War",
      "url": "https://www.goodreads.com/book/show/8914.The_First_World_War",
      "id": "11817",
      "cover_url": "https://images-na.ssl-images-amazon.com/images/S/compressed.photo.goodreads.com/books/1403194704i/8914.jpg",
      "authors": [
        "John Keegan"
      ],
      "genres": [
        "history",
        "non-fiction",
        "war",
        "world-war-i",
        "military-history",
        "military-fiction",
        "european-history"
      ],
      "rating": 4.03,
      "ratings": 14921,
      "reviews": 591
    },
    {
      "title": "D DAY Through German Eyes - The Hidden Story of June 6th 1944",
      "url": "https://www.goodreads.com/book/show/25343241-d-day-through-german-eyes---the-hidden-story-of-june-6th-1944",
      "id": "45081341",
      "cover_url": "https://images-na.ssl-images-amazon.com/images/S/compressed.photo.goodreads.com/books/1437456056i/25343241.jpg",
      "authors": [
        "Holger Eckhertz"
      ],
      "genres": [
        "history",
        "non-fiction",
        "war",
        "world-war-ii",
        "military-fiction",
        "military-history",
        "historical"
      ],
      "rating": 4.03,
      "ratings": 14851,
      "reviews": 751
    },
    {
      "title": "Bravo Two-zero",
      "url": "https://www.goodreads.com/book/show/22202.Bravo_Two_zero",
      "id": "950909",
      "cover_url": "https://images-na.ssl-images-amazon.com/images/S/compressed.photo.goodreads.com/books/1348022403i/22202.jpg",
      "authors": [
        "Andy McNab"
      ],
      "genres": [
        "military-fiction",
        "non-fiction",
        "war",
        "history",
        "biography",
        "military-history",
        "memoir"
      ],
      "rating": 4.11,
      "ratings": 14811,
      "reviews": 447
    },
    {
      "title": "The Day of Battle: The War in Sicily and Italy, 1943-1944",
      "url": "https://www.goodreads.com/book/show/716532.The_Day_of_Battle",
      "id": "702783",
      "cover_url": "https://images-na.ssl-images-amazon.com/images/S/compressed.photo.goodreads.com/books/1442525486i/716532.jpg",
      "authors": [
        "Rick Atkinson"
      ],
      "genres": [
        "history",
        "non-fiction",
        "military-history",
        "world-war-ii",
        "military-fiction",
        "war",
        "american-history"
      ],
      "rating": 4.35,
      "ratings": 14673,
      "reviews": 750
    },
    {
      "title": "Chickenhawk",
      "url": "https://www.goodreads.com/book/show/63699.Chickenhawk",
      "id": "61856",
      "cover_url": "https://images-na.ssl-images-amazon.com/images/S/compressed.photo.goodreads.com/books/1391026065i/63699.jpg",
      "authors": [
        "Robert Mason"
      ],
      "genres": [
        "history",
        "war",
        "non-fiction",
        "military-fiction",
        "biography",
        "military-history",
        "memoir"
      ],
      "rating": 4.24,
      "ratings": 14228,
      "reviews": 636
    },
    {
      "title": "The Pacific",
      "url": "https://www.goodreads.com/book/show/7494887-the-pacific",
      "id": "9646479",
      "cover_url": "https://images-na.ssl-images-amazon.com/images/S/compressed.photo.goodreads.com/books/1347284164i/7494887.jpg",
      "authors": [
        "Hugh Ambrose"
      ],
      "genres": [
        "history",
        "non-fiction",
        "war",
        "military-fiction",
        "world-war-ii",
        "military-history",
        "biography"
      ],
      "rating": 4.13,
      "ratings": 13614,
      "reviews": 392
    },
    {
      "title": "American Caesar: Douglas MacArthur 1880-1964",
      "url": "https://www.goodreads.com/book/show/20949.American_Caesar",
      "id": "268055",
      "cover_url": "https://images-na.ssl-images-amazon.com/images/S/compressed.photo.goodreads.com/books/1410810799i/20949.jpg",
      "authors": [
        "William Manchester"
      ],
      "genres": [
        "biography",
        "history",
        "non-fiction",
        "military-fiction",
        "american-history",
        "military-history",
        "world-war-ii"
      ],
      "rating": 4.08,
      "ratings": 13600,
      "reviews": 382
    },
    {
      "title": "Enemy at the Gates: The Battle for Stalingrad",
      "url": "https://www.goodreads.com/book/show/435556.Enemy_at_the_Gates",
      "id": "3999",
      "cover_url": "https://images-na.ssl-images-amazon.com/images/S/compressed.photo.goodreads.com/books/1498139456i/435556.jpg",
      "authors": [
        "William Craig"
      ],
      "genres": [
        "history",
        "non-fiction",
        "war",
        "world-war-ii",
        "military-history",
        "military-fiction",
        "russia"
      ],
      "rating": 4.22,
      "ratings": 13553,
      "reviews": 493
    },
    {
      "title": "Outlaw Platoon: Heroes, Renegades, Infidels, and the Brotherhood of War in Afghanistan",
      "url": "https://www.goodreads.com/book/show/12990404-outlaw-platoon",
      "id": "18150348",
      "cover_url": "https://images-na.ssl-images-amazon.com/images/S/compressed.photo.goodreads.com/books/1353154399i/12990404.jpg",
      "authors": [
        "Sean  Parnell"
      ],
      "genres": [
        "military-fiction",
        "non-fiction",
        "history",
        "war",
        "military-history",
        "memoir",
        "biography"
      ],
      "rating": 4.39,
      "ratings": 12119,
      "reviews": 810
    },
    {
      "title": "The Conquest of Gaul",
      "url": "https://www.goodreads.com/book/show/592167.The_Conquest_of_Gaul",
      "id": "1978328",
      "cover_url": "https://images-na.ssl-images-amazon.com/images/S/compressed.photo.goodreads.com/books/1683453362i/592167.jpg",
      "authors": [
        "Gaius Julius Caesar"
      ],
      "genres": [
        "history",
        "classics",
        "non-fiction",
        "ancient-history",
        "war",
        "military-history",
        "biography"
      ],
      "rating": 4.01,
      "ratings": 12043,
      "reviews": 591
    },
    {
      "title": "A Bright Shining Lie: John Paul Vann and America in Vietnam",
      "url": "https://www.goodreads.com/book/show/417640.A_Bright_Shining_Lie",
      "id": "71026",
      "cover_url": "https://images-na.ssl-images-amazon.com/images/S/compressed.photo.goodreads.com/books/1350053421i/417640.jpg",
      "authors": [
        "Neil Sheehan"
      ],
      "genres": [
        "history",
        "non-fiction",
        "war",
        "biography",
        "american-history",
        "military-fiction",
        "military-history"
      ],
      "rating": 4.23,
      "ratings": 12028,
      "reviews": 474
    },
    {
      "title": "The Sleepwalkers: How Europe Went to War in 1914",
      "url": "https://www.goodreads.com/book/show/18669169-the-sleepwalkers",
      "id": "21905061",
      "cover_url": "https://images-na.ssl-images-amazon.com/images/S/compressed.photo.goodreads.com/books/1384804367i/18669169.jpg",
      "authors": [
        "Christopher   Clark"
      ],
      "genres": [
        "history",
        "non-fiction",
        "world-war-i",
        "war",
        "politics",
        "european-history",
        "military-history"
      ],
      "rating": 4.21,
      "ratings": 11502,
      "reviews": 1133
    },
    {
      "title": "The Forgotten 500: The Untold Story of the Men Who Risked All For the Greatest Rescue Mission of World War II",
      "url": "https://www.goodreads.com/book/show/1707116.The_Forgotten_500",
      "id": "1704281",
      "cover_url": "https://images-na.ssl-images-amazon.com/images/S/compressed.photo.goodreads.com/books/1436816506i/1707116.jpg",
      "authors": [
        "Gregory A. Freeman"
      ],
      "genres": [
        "history",
        "non-fiction",
        "world-war-ii",
        "military-fiction",
        "war",
        "military-history",
        "historical"
      ],
      "rating": 4.06,
      "ratings": 11462,
      "reviews": 886
    },
    {
      "title": "Rogue Heroes: The History of the SAS, Britain's Secret Special Forces Unit That Sabotaged the Nazis and Changed the Nature of War",
      "url": "https://www.goodreads.com/book/show/28503837-rogue-heroes",
      "id": "48656119",
      "cover_url": "https://images-na.ssl-images-amazon.com/images/S/compressed.photo.goodreads.com/books/1460626650i/28503837.jpg",
      "authors": [
        "Ben Macintyre"
      ],
      "genres": [
        "history",
        "non-fiction",
        "world-war-ii",
        "military-fiction",
        "war",
        "military-history",
        "audiobook"
      ],
      "rating": 4.35,
      "ratings": 11209,
      "reviews": 973
    },
    {
      "title": "D-Day: The Battle for Normandy",
      "url": "https://www.goodreads.com/book/show/2455549.D_Day",
      "id": "2462744",
      "cover_url": "https://images-na.ssl-images-amazon.com/images/S/compressed.photo.goodreads.com/books/1348623855i/2455549.jpg",
      "authors": [
        "Antony Beevor"
      ],
      "genres": [
        "history",
        "non-fiction",
        "war",
        "world-war-ii",
        "military-history",
        "military-fiction",
        "france"
      ],
      "rating": 4.17,
      "ratings": 11164,
      "reviews": 558
    },
    {
      "title": "The Forgotten Soldier",
      "url": "https://www.goodreads.com/book/show/102305.The_Forgotten_Soldier",
      "id": "98639",
      "cover_url": "https://images-na.ssl-images-amazon.com/images/S/compressed.photo.goodreads.com/books/1347798004i/102305.jpg",
      "authors": [
        "Guy Sajer"
      ],
      "genres": [
        "history",
        "non-fiction",
        "war",
        "military-fiction",
        "world-war-ii",
        "biography",
        "military-history"
      ],
      "rating": 4.37,
      "ratings": 11162,
      "reviews": 697
    },
    {
      "title": "The Forever War",
      "url": "https://www.goodreads.com/book/show/2517439.The_Forever_War",
      "id": "2524836",
      "cover_url": "https://images-na.ssl-images-amazon.com/images/S/compressed.photo.goodreads.com/books/1320478597i/2517439.jpg",
      "authors": [
        "Dexter Filkins"
      ],
      "genres": [
        "non-fiction",
        "history",
        "war",
        "politics",
        "military-fiction",
        "journalism",
        "military-history"
      ],
      "rating": 4.12,
      "ratings": 10985,
      "reviews": 973
    },
    {
      "title": "One Bullet Away: The Making of a Marine Officer",
      "url": "https://www.goodreads.com/book/show/116478.One_Bullet_Away",
      "id": "112166",
      "cover_url": "https://images-na.ssl-images-amazon.com/images/S/compressed.photo.goodreads.com/books/1442851756i/116478.jpg",
      "authors": [
        "Nathaniel Fick"
      ],
      "genres": [
        "military-fiction",
        "non-fiction",
        "war",
        "history",
        "biography",
        "military-history",
        "memoir"
      ],
      "rating": 4.18,
      "ratings": 10862,
      "reviews": 480
    },
    {
      "title": "On Killing: The Psychological Cost of Learning to Kill in War and Society",
      "url": "https://www.goodreads.com/book/show/78127.On_Killing",
      "id": "804474",
      "cover_url": "https://images-na.ssl-images-amazon.com/images/S/compressed.photo.goodreads.com/books/1373461495i/78127.jpg",
      "authors": [
        "Dave Grossman"
      ],
      "genres": [
        "psychology",
        "non-fiction",
        "military-fiction",
        "war",
        "history",
        "science",
        "military-history"
      ],
      "rating": 4.12,
      "ratings": 10845,
      "reviews": 915
    },
    {
      "title": "The Last Stand of the Tin Can Sailors: The Extraordinary World War II Story of the U.S. Navy's Finest Hour",
      "url": "https://www.goodreads.com/book/show/5400.The_Last_Stand_of_the_Tin_Can_Sailors",
      "id": "134539",
      "cover_url": "https://images-na.ssl-images-amazon.com/images/S/compressed.photo.goodreads.com/books/1388202712i/5400.jpg",
      "authors": [
        "James D. Hornfischer"
      ],
      "genres": [
        "history",
        "non-fiction",
        "military-fiction",
        "world-war-ii",
        "war",
        "military-history",
        "naval-history"
      ],
      "rating": 4.34,
      "ratings": 10673,
      "reviews": 651
    },
    {
      "title": "Inside Delta Force: The Story of America's Elite Counterterrorist Unit",
      "url": "https://www.goodreads.com/book/show/115587.Inside_Delta_Force",
      "id": "111311",
      "cover_url": "https://images-na.ssl-images-amazon.com/images/S/compressed.photo.goodreads.com/books/1320416478i/115587.jpg",
      "authors": [
        "Eric L. Haney"
      ],
      "genres": [
        "military-fiction",
        "non-fiction",
        "history",
        "war",
        "military-history",
        "biography",
        "memoir"
      ],
      "rating": 4.17,
      "ratings": 10649,
      "reviews": 443
    },
    {
      "title": "The Operator: Firing the Shots that Killed Osama bin Laden and My Years as a SEAL Team Warrior",
      "url": "https://www.goodreads.com/book/show/34127824-the-operator",
      "id": "55162697",
      "cover_url": "https://images-na.ssl-images-amazon.com/images/S/compressed.photo.goodreads.com/books/1486335309i/34127824.jpg",
      "authors": [
        "Robert  O'Neill"
      ],
      "genres": [
        "military-fiction",
        "non-fiction",
        "history",
        "biography",
        "war",
        "memoir",
        "military-history"
      ],
      "rating": 4.42,
      "ratings": 10275,
      "reviews": 667
    },
    {
      "title": "Pegasus Bridge: June 6, 1944",
      "url": "https://www.goodreads.com/book/show/49254.Pegasus_Bridge",
      "id": "862849",
      "cover_url": "https://images-na.ssl-images-amazon.com/images/S/compressed.photo.goodreads.com/books/1525279642i/49254.jpg",
      "authors": [
        "Stephen E. Ambrose"
      ],
      "genres": [
        "history",
        "non-fiction",
        "military-history",
        "military-fiction",
        "war",
        "world-war-ii",
        "historical"
      ],
      "rating": 4.13,
      "ratings": 10180,
      "reviews": 327
    },
    {
      "title": "Marine Sniper: 93 Confirmed Kills",
      "url": "https://www.goodreads.com/book/show/55764.Marine_Sniper",
      "id": "54340",
      "cover_url": "https://images-na.ssl-images-amazon.com/images/S/compressed.photo.goodreads.com/books/1388244046i/55764.jpg",
      "authors": [
        "Charles Henderson"
      ],
      "genres": [
        "military-fiction",
        "history",
        "non-fiction",
        "war",
        "biography",
        "military-history",
        "biography-memoir"
      ],
      "rating": 4.3,
      "ratings": 10044,
      "reviews": 352
    },
    {
      "title": "The Great Escape",
      "url": "https://www.goodreads.com/book/show/1281677.The_Great_Escape",
      "id": "922965",
      "cover_url": "https://images-na.ssl-images-amazon.com/images/S/compressed.photo.goodreads.com/books/1348407573i/1281677.jpg",
      "authors": [
        "Paul Brickhill"
      ],
      "genres": [
        "history",
        "non-fiction",
        "war",
        "world-war-ii",
        "military-fiction",
        "historical",
        "military-history"
      ],
      "rating": 4.21,
      "ratings": 9904,
      "reviews": 529
    },
    {
      "title": "Inferno: The World at War, 1939-1945",
      "url": "https://www.goodreads.com/book/show/11256415-inferno",
      "id": "16183109",
      "cover_url": "https://images-na.ssl-images-amazon.com/images/S/compressed.photo.goodreads.com/books/1320563685i/11256415.jpg",
      "authors": [
        "Max Hastings"
      ],
      "genres": [
        "history",
        "non-fiction",
        "war",
        "world-war-ii",
        "military-history",
        "military-fiction",
        "world-history"
      ],
      "rating": 4.34,
      "ratings": 9820,
      "reviews": 795
    },
    {
      "title": "The Guns at Last Light: The War in Western Europe, 1944-1945",
      "url": "https://www.goodreads.com/book/show/16044941-the-guns-at-last-light",
      "id": "21858205",
      "cover_url": "https://images-na.ssl-images-amazon.com/images/S/compressed.photo.goodreads.com/books/1435169033i/16044941.jpg",
      "authors": [
        "Rick Atkinson"
      ],
      "genres": [
        "history",
        "non-fiction",
        "world-war-ii",
        "military-history",
        "war",
        "military-fiction",
        "american-history"
      ],
      "rating": 4.46,
      "ratings": 9808,
      "reviews": 864
    },
    {
      "title": "Blind Man's Bluff: The Untold Story of American Submarine Espionage",
      "url": "https://www.goodreads.com/book/show/42343.Blind_Man_s_Bluff",
      "id": "41833",
      "cover_url": "https://images-na.ssl-images-amazon.com/images/S/compressed.photo.goodreads.com/books/1401046241i/42343.jpg",
      "authors": [
        "Sherry Sontag"
      ],
      "genres": [
        "history",
        "non-fiction",
        "military-fiction",
        "military-history",
        "espionage",
        "war",
        "naval-history"
      ],
      "rating": 4.22,
      "ratings": 9441,
      "reviews": 581
    },
    {
      "title": "The Second World War",
      "url": "https://www.goodreads.com/book/show/13528287-the-second-world-war",
      "id": "18458500",
      "cover_url": "https://images-na.ssl-images-amazon.com/images/S/compressed.photo.goodreads.com/books/1338581873i/13528287.jpg",
      "authors": [
        "Antony Beevor"
      ],
      "genres": [
        "history",
        "non-fiction",
        "war",
        "world-war-ii",
        "military-history",
        "military-fiction",
        "politics"
      ],
      "rating": 4.38,
      "ratings": 9236,
      "reviews": 687
    },
    {
      "title": "The Rising Tide",
      "url": "https://www.goodreads.com/book/show/29917.The_Rising_Tide",
      "id": "168570",
      "cover_url": "https://images-na.ssl-images-amazon.com/images/S/compressed.photo.goodreads.com/books/1388535171i/29917.jpg",
      "authors": [
        "Jeff Shaara"
      ],
      "genres": [
        "historical-fiction",
        "fiction",
        "world-war-ii",
        "war",
        "military-fiction",
        "historical",
        "military-history"
      ],
      "rating": 4.15,
      "ratings": 8881,
      "reviews": 527
    },
    {
      "title": "The Coldest Winter: America and the Korean War",
      "url": "https://www.goodreads.com/book/show/448135.The_Coldest_Winter",
      "id": "2171159",
      "cover_url": "https://images-na.ssl-images-amazon.com/images/S/compressed.photo.goodreads.com/books/1326474263i/448135.jpg",
      "authors": [
        "David Halberstam"
      ],
      "genres": [
        "history",
        "non-fiction",
        "war",
        "military-history",
        "military-fiction",
        "american-history",
        "politics"
      ],
      "rating": 4.21,
      "ratings": 8724,
      "reviews": 817
    },
    {
      "title": "The Good Soldiers",
      "url": "https://www.goodreads.com/book/show/6633912-the-good-soldiers",
      "id": "6828305",
      "cover_url": "https://images-na.ssl-images-amazon.com/images/S/compressed.photo.goodreads.com/books/1442327825i/6633912.jpg",
      "authors": [
        "David Finkel"
      ],
      "genres": [
        "non-fiction",
        "war",
        "history",
        "military-fiction",
        "military-history",
        "politics",
        "journalism"
      ],
      "rating": 4.21,
      "ratings": 8415,
      "reviews": 925
    },
    {
      "title": "Horse Soldiers: The Extraordinary Story of a Band of US Soldiers Who Rode to Victory in Afghanistan",
      "url": "https://www.goodreads.com/book/show/4645750-horse-soldiers",
      "id": "3681388",
      "cover_url": "https://images-na.ssl-images-amazon.com/images/S/compressed.photo.goodreads.com/books/1347358066i/4645750.jpg",
      "authors": [
        "Doug Stanton"
      ],
      "genres": [
        "history",
        "non-fiction",
        "military-fiction",
        "war",
        "military-history",
        "american-history",
        "biography"
      ],
      "rating": 4.14,
      "ratings": 8357,
      "reviews": 630
    },
    {
      "title": "Pacific Crucible: War at Sea in the Pacific, 1941-1942",
      "url": "https://www.goodreads.com/book/show/13707735-pacific-crucible",
      "id": "15872697",
      "cover_url": "https://images-na.ssl-images-amazon.com/images/S/compressed.photo.goodreads.com/books/1347983136i/13707735.jpg",
      "authors": [
        "Ian W. Toll"
      ],
      "genres": [
        "history",
        "non-fiction",
        "world-war-ii",
        "military-history",
        "military-fiction",
        "war",
        "american-history"
      ],
      "rating": 4.59,
      "ratings": 8350,
      "reviews": 735
    },
    {
      "title": "The Face of Battle: A Study of Agincourt, Waterloo and the Somme",
      "url": "https://www.goodreads.com/book/show/275833.The_Face_of_Battle",
      "id": "1372320",
      "cover_url": "https://images-na.ssl-images-amazon.com/images/S/compressed.photo.goodreads.com/books/1485648112i/275833.jpg",
      "authors": [
        "John Keegan"
      ],
      "genres": [
        "history",
        "non-fiction",
        "military-history",
        "military-fiction",
        "war",
        "european-history",
        "world-war-i"
      ],
      "rating": 4.13,
      "ratings": 8179,
      "reviews": 389
    },
    {
      "title": "A World Undone: The Story of the Great War, 1914 to 1918",
      "url": "https://www.goodreads.com/book/show/100834.A_World_Undone",
      "id": "97230",
      "cover_url": "https://images-na.ssl-images-amazon.com/images/S/compressed.photo.goodreads.com/books/1171470414i/100834.jpg",
      "authors": [
        "G.J. Meyer"
      ],
      "genres": [
        "history",
        "non-fiction",
        "world-war-i",
        "war",
        "military-history",
        "military-fiction",
        "audiobook"
      ],
      "rating": 4.35,
      "ratings": 8053,
      "reviews": 740
    },
    {
      "title": "To Hell and Back",
      "url": "https://www.goodreads.com/book/show/300674.To_Hell_and_Back",
      "id": "291743",
      "cover_url": "https://images-na.ssl-images-amazon.com/images/S/compressed.photo.goodreads.com/books/1344865109i/300674.jpg",
      "authors": [
        "Audie Murphy"
      ],
      "genres": [
        "history",
        "non-fiction",
        "biography",
        "military-fiction",
        "world-war-ii",
        "war",
        "military-history"
      ],
      "rating": 4.25,
      "ratings": 7989,
      "reviews": 368
    },
    {
      "title": "The Civil War: A Narrative",
      "url": "https://www.goodreads.com/book/show/44234.The_Civil_War",
      "id": "43597",
      "cover_url": "https://images-na.ssl-images-amazon.com/images/S/compressed.photo.goodreads.com/books/1313254390i/44234.jpg",
      "authors": [
        "Shelby Foote"
      ],
      "genres": [
        "history",
        "civil-war",
        "non-fiction",
        "american-history",
        "war",
        "american-civil-war",
        "military-history"
      ],
      "rating": 4.53,
      "ratings": 7852,
      "reviews": 377
    },
    {
      "title": "Waterloo: The True Story of Four Days, Three Armies and Three Battles",
      "url": "https://www.goodreads.com/book/show/22007249-waterloo",
      "id": "41318790",
      "cover_url": "https://images-na.ssl-images-amazon.com/images/S/compressed.photo.goodreads.com/books/1398301621i/22007249.jpg",
      "authors": [
        "Bernard Cornwell"
      ],
      "genres": [
        "history",
        "non-fiction",
        "war",
        "military-history",
        "military-fiction",
        "european-history",
        "historical"
      ],
      "rating": 4.22,
      "ratings": 7802,
      "reviews": 767
    },
    {
      "title": "The Longest Winter: The Battle of the Bulge and the Epic Story of World War II's Most Decorated Platoon",
      "url": "https://www.goodreads.com/book/show/1312031.The_Longest_Winter",
      "id": "587010",
      "cover_url": "https://images-na.ssl-images-amazon.com/images/S/compressed.photo.goodreads.com/books/1387740265i/1312031.jpg",
      "authors": [
        "Alex Kershaw"
      ],
      "genres": [
        "history",
        "non-fiction",
        "world-war-ii",
        "war",
        "military-history",
        "military-fiction",
        "biography"
      ],
      "rating": 4.17,
      "ratings": 7643,
      "reviews": 363
    },
    {
      "title": "Vietnam: A History",
      "url": "https://www.goodreads.com/book/show/96110.Vietnam",
      "id": "92632",
      "cover_url": "https://images-na.ssl-images-amazon.com/images/S/compressed.photo.goodreads.com/books/1535986107i/96110.jpg",
      "authors": [
        "Stanley Karnow"
      ],
      "genres": [
        "history",
        "non-fiction",
        "war",
        "military-fiction",
        "military-history",
        "american-history",
        "politics"
      ],
      "rating": 4.12,
      "ratings": 7628,
      "reviews": 315
    },
    {
      "title": "Fiasco: The American Military Adventure in Iraq",
      "url": "https://www.goodreads.com/book/show/86342.Fiasco",
      "id": "1465267",
      "cover_url": "https://images-na.ssl-images-amazon.com/images/S/compressed.photo.goodreads.com/books/1442857845i/86342.jpg",
      "authors": [
        "Thomas E. Ricks"
      ],
      "genres": [
        "history",
        "non-fiction",
        "politics",
        "war",
        "military-fiction",
        "military-history",
        "american-history"
      ],
      "rating": 4.08,
      "ratings": 7548,
      "reviews": 497
    },
    {
      "title": "The Steel Wave",
      "url": "https://www.goodreads.com/book/show/2047408.The_Steel_Wave",
      "id": "6645517",
      "cover_url": "https://images-na.ssl-images-amazon.com/images/S/compressed.photo.goodreads.com/books/1441410840i/2047408.jpg",
      "authors": [
        "Jeff Shaara"
      ],
      "genres": [
        "historical-fiction",
        "fiction",
        "war",
        "world-war-ii",
        "historical",
        "military-fiction",
        "military-history"
      ],
      "rating": 4.27,
      "ratings": 7327,
      "reviews": 388
    },
    {
      "title": "Boyd: The Fighter Pilot Who Changed the Art of War",
      "url": "https://www.goodreads.com/book/show/38840.Boyd",
      "id": "38568",
      "cover_url": "https://images-na.ssl-images-amazon.com/images/S/compressed.photo.goodreads.com/books/1436893688i/38840.jpg",
      "authors": [
        "Robert Coram"
      ],
      "genres": [
        "biography",
        "history",
        "non-fiction",
        "military-fiction",
        "war",
        "aviation",
        "military-history"
      ],
      "rating": 4.16,
      "ratings": 7287,
      "reviews": 535
    },
    {
      "title": "Fields of Fire",
      "url": "https://www.goodreads.com/book/show/198289.Fields_of_Fire",
      "id": "1936719",
      "cover_url": "https://images-na.ssl-images-amazon.com/images/S/compressed.photo.goodreads.com/books/1388179875i/198289.jpg",
      "authors": [
        "James Webb"
      ],
      "genres": [
        "fiction",
        "historical-fiction",
        "war",
        "military-fiction",
        "military-history",
        "novels",
        "historical"
      ],
      "rating": 4.2,
      "ratings": 7269,
      "reviews": 312
    },
    {
      "title": "Red Platoon: A True Story of American Valor",
      "url": "https://www.goodreads.com/book/show/26109393-red-platoon",
      "id": "46054782",
      "cover_url": "https://images-na.ssl-images-amazon.com/images/S/compressed.photo.goodreads.com/books/1457890793i/26109393.jpg",
      "authors": [
        "Clinton Romesha"
      ],
      "genres": [
        "military-fiction",
        "history",
        "war",
        "non-fiction",
        "military-history",
        "memoir",
        "biography"
      ],
      "rating": 4.57,
      "ratings": 7111,
      "reviews": 603
    },
    {
      "title": "Armageddon: The Battle for Germany, 1944-1945",
      "url": "https://www.goodreads.com/book/show/55404.Armageddon",
      "id": "53993",
      "cover_url": "https://images-na.ssl-images-amazon.com/images/S/compressed.photo.goodreads.com/books/1388216136i/55404.jpg",
      "authors": [
        "Max Hastings"
      ],
      "genres": [
        "history",
        "non-fiction",
        "world-war-ii",
        "military-history",
        "war",
        "military-fiction",
        "germany"
      ],
      "rating": 4.27,
      "ratings": 7107,
      "reviews": 236
    },
    {
      "title": "The Civil War, Vol. 2: Fredericksburg to Meridian",
      "url": "https://www.goodreads.com/book/show/373593.The_Civil_War_Vol_2",
      "id": "6864001",
      "cover_url": "https://images-na.ssl-images-amazon.com/images/S/compressed.photo.goodreads.com/books/1345036160i/373593.jpg",
      "authors": [
        "Shelby Foote"
      ],
      "genres": [
        "history",
        "civil-war",
        "non-fiction",
        "american-history",
        "american-civil-war",
        "war",
        "military-history"
      ],
      "rating": 4.53,
      "ratings": 7064,
      "reviews": 251
    },
    {
      "title": "Service: A Navy SEAL at War",
      "url": "https://www.goodreads.com/book/show/13515711-service",
      "id": "19072323",
      "cover_url": "https://images-na.ssl-images-amazon.com/images/S/compressed.photo.goodreads.com/books/1334084570i/13515711.jpg",
      "authors": [
        "Marcus Luttrell"
      ],
      "genres": [
        "military-fiction",
        "non-fiction",
        "war",
        "history",
        "biography",
        "military-history",
        "memoir"
      ],
      "rating": 4.3,
      "ratings": 7030,
      "reviews": 317
    },
    {
      "title": "The Civil War, Vol. 3: Red River to Appomattox",
      "url": "https://www.goodreads.com/book/show/874419.The_Civil_War_Vol_3",
      "id": "6864002",
      "cover_url": "https://images-na.ssl-images-amazon.com/images/S/compressed.photo.goodreads.com/books/1345039708i/874419.jpg",
      "authors": [
        "Shelby Foote"
      ],
      "genres": [
        "history",
        "civil-war",
        "non-fiction",
        "american-history",
        "american-civil-war",
        "war",
        "military-history"
      ],
      "rating": 4.54,
      "ratings": 6997,
      "reviews": 259
    },
    {
      "title": "The Second World War",
      "url": "https://www.goodreads.com/book/show/55200.The_Second_World_War",
      "id": "2507815",
      "cover_url": "https://images-na.ssl-images-amazon.com/images/S/compressed.photo.goodreads.com/books/1388244781i/55200.jpg",
      "authors": [
        "John Keegan"
      ],
      "genres": [
        "history",
        "non-fiction",
        "war",
        "military-history",
        "world-war-ii",
        "military-fiction",
        "world-history"
      ],
      "rating": 4.22,
      "ratings": 6946,
      "reviews": 299
    },
    {
      "title": "Neptune's Inferno: The U.S. Navy at Guadalcanal",
      "url": "https://www.goodreads.com/book/show/8575701-neptune-s-inferno",
      "id": "13444597",
      "cover_url": "https://images-na.ssl-images-amazon.com/images/S/compressed.photo.goodreads.com/books/1320403084i/8575701.jpg",
      "authors": [
        "James D. Hornfischer"
      ],
      "genres": [
        "history",
        "non-fiction",
        "military-fiction",
        "military-history",
        "world-war-ii",
        "war",
        "naval-history"
      ],
      "rating": 4.28,
      "ratings": 6826,
      "reviews": 507
    },
    {
      "title": "House to House: An Epic Memoir of War",
      "url": "https://www.goodreads.com/book/show/1554307.House_to_House",
      "id": "1546752",
      "cover_url": "https://images-na.ssl-images-amazon.com/images/S/compressed.photo.goodreads.com/books/1440124085i/1554307.jpg",
      "authors": [
        "David Bellavia"
      ],
      "genres": [
        "military-fiction",
        "non-fiction",
        "history",
        "war",
        "military-history",
        "memoir",
        "biography"
      ],
      "rating": 4.31,
      "ratings": 6822,
      "reviews": 425
    },
    {
      "title": "Six Frigates: The Epic History of the Founding of the U. S. Navy",
      "url": "https://www.goodreads.com/book/show/39000.Six_Frigates",
      "id": "1525986",
      "cover_url": "https://images-na.ssl-images-amazon.com/images/S/compressed.photo.goodreads.com/books/1329071512i/39000.jpg",
      "authors": [
        "Ian W. Toll"
      ],
      "genres": [
        "history",
        "non-fiction",
        "american-history",
        "military-fiction",
        "military-history",
        "war",
        "naval-history"
      ],
      "rating": 4.37,
      "ratings": 6817,
      "reviews": 558
    },
    {
      "title": "Dreadnought: Britain, Germany, and the Coming of the Great War",
      "url": "https://www.goodreads.com/book/show/209889.Dreadnought",
      "id": "1415747",
      "cover_url": "https://images-na.ssl-images-amazon.com/images/S/compressed.photo.goodreads.com/books/1386924183i/209889.jpg",
      "authors": [
        "Robert K. Massie"
      ],
      "genres": [
        "history",
        "non-fiction",
        "world-war-i",
        "military-history",
        "war",
        "military-fiction",
        "european-history"
      ],
      "rating": 4.31,
      "ratings": 6679,
      "reviews": 368
    },
    {
      "title": "The March of Folly",
      "url": "https://www.goodreads.com/book/show/10302.The_March_of_Folly",
      "id": "279244",
      "cover_url": "https://images-na.ssl-images-amazon.com/images/S/compressed.photo.goodreads.com/books/1404483483i/10302.jpg",
      "authors": [
        "Barbara W. Tuchman"
      ],
      "genres": [
        "history",
        "non-fiction",
        "politics",
        "war",
        "world-history",
        "military-history",
        "military-fiction"
      ],
      "rating": 4.02,
      "ratings": 6666,
      "reviews": 546
    },
    {
      "title": "The Last Battle: The Classic History of the Battle for Berlin",
      "url": "https://www.goodreads.com/book/show/84370.The_Last_Battle",
      "id": "1753998",
      "cover_url": "https://images-na.ssl-images-amazon.com/images/S/compressed.photo.goodreads.com/books/1620463245i/84370.jpg",
      "authors": [
        "Cornelius Ryan"
      ],
      "genres": [
        "history",
        "non-fiction",
        "world-war-ii",
        "war",
        "military-history",
        "military-fiction",
        "germany"
      ],
      "rating": 4.23,
      "ratings": 6639,
      "reviews": 227
    },
    {
      "title": "Rogue Warrior",
      "url": "https://www.goodreads.com/book/show/302424.Rogue_Warrior",
      "id": "2636428",
      "cover_url": "https://images-na.ssl-images-amazon.com/images/S/compressed.photo.goodreads.com/books/1382902946i/302424.jpg",
      "authors": [
        "Richard Marcinko"
      ],
      "genres": [
        "military-fiction",
        "non-fiction",
        "biography",
        "history",
        "military-history",
        "war",
        "autobiography"
      ],
      "rating": 4.01,
      "ratings": 6527,
      "reviews": 242
    },
    {
      "title": "Imperial Life in the Emerald City: Inside Iraq's Green Zone",
      "url": "https://www.goodreads.com/book/show/22121.Imperial_Life_in_the_Emerald_City",
      "id": "1275660",
      "cover_url": "https://images-na.ssl-images-amazon.com/images/S/compressed.photo.goodreads.com/books/1388184155i/22121.jpg",
      "authors": [
        "Rajiv Chandrasekaran"
      ],
      "genres": [
        "non-fiction",
        "history",
        "politics",
        "war",
        "military-fiction",
        "journalism",
        "military-history"
      ],
      "rating": 4.04,
      "ratings": 6386,
      "reviews": 657
    },
    {
      "title": "Empires of the Sea: The Final Battle for the Mediterranean, 1521 - 1580",
      "url": "https://www.goodreads.com/book/show/3418555-empires-of-the-sea",
      "id": "2456291",
      "cover_url": "https://images-na.ssl-images-amazon.com/images/S/compressed.photo.goodreads.com/books/1332815546i/3418555.jpg",
      "authors": [
        "Roger Crowley"
      ],
      "genres": [
        "history",
        "non-fiction",
        "european-history",
        "military-history",
        "war",
        "military-fiction",
        "world-history"
      ],
      "rating": 4.29,
      "ratings": 6134,
      "reviews": 512
    },
    {
      "title": "The Liberator: One World War II Soldier's 500-Day Odyssey from the Beaches of Sicily to the Gates of Dachau",
      "url": "https://www.goodreads.com/book/show/13532239-the-liberator",
      "id": "19093915",
      "cover_url": "https://images-na.ssl-images-amazon.com/images/S/compressed.photo.goodreads.com/books/1520346584i/13532239.jpg",
      "authors": [
        "Alex Kershaw"
      ],
      "genres": [
        "history",
        "non-fiction",
        "world-war-ii",
        "war",
        "biography",
        "military-fiction",
        "military-history"
      ],
      "rating": 4.27,
      "ratings": 6125,
      "reviews": 612
    },
    {
      "title": "Andrew Jackson and the Miracle of New Orleans: The Battle That Shaped America's Destiny",
      "url": "https://www.goodreads.com/book/show/34350212-andrew-jackson-and-the-miracle-of-new-orleans",
      "id": "55426339",
      "cover_url": "https://images-na.ssl-images-amazon.com/images/S/compressed.photo.goodreads.com/books/1492221685i/34350212.jpg",
      "authors": [
        "Brian Kilmeade"
      ],
      "genres": [
        "history",
        "non-fiction",
        "biography",
        "american-history",
        "presidents",
        "military-history",
        "war"
      ],
      "rating": 4.09,
      "ratings": 6079,
      "reviews": 641
    },
    {
      "title": "The Outpost: An Untold Story of American Valor",
      "url": "https://www.goodreads.com/book/show/13528359-the-outpost",
      "id": "19082186",
      "cover_url": "https://images-na.ssl-images-amazon.com/images/S/compressed.photo.goodreads.com/books/1393724932i/13528359.jpg",
      "authors": [
        "Jake Tapper"
      ],
      "genres": [
        "history",
        "non-fiction",
        "military-fiction",
        "war",
        "military-history",
        "american-history",
        "audiobook"
      ],
      "rating": 4.33,
      "ratings": 5980,
      "reviews": 483
    },
    {
      "title": "The British Are Coming: The War for America, Lexington to Princeton, 1775-1777",
      "url": "https://www.goodreads.com/book/show/41812830-the-british-are-coming",
      "id": "65247139",
      "cover_url": "https://images-na.ssl-images-amazon.com/images/S/compressed.photo.goodreads.com/books/1538524326i/41812830.jpg",
      "authors": [
        "Rick Atkinson"
      ],
      "genres": [
        "history",
        "non-fiction",
        "american-history",
        "american-revolution",
        "military-history",
        "american-revolutionary-war",
        "war"
      ],
      "rating": 4.43,
      "ratings": 5973,
      "reviews": 832
    },
    {
      "title": "The Great War and Modern Memory",
      "url": "https://www.goodreads.com/book/show/154472.The_Great_War_and_Modern_Memory",
      "id": "149094",
      "cover_url": "https://images-na.ssl-images-amazon.com/images/S/compressed.photo.goodreads.com/books/1347954655i/154472.jpg",
      "authors": [
        "Paul Fussell"
      ],
      "genres": [
        "history",
        "non-fiction",
        "world-war-i",
        "war",
        "literary-criticism",
        "military-fiction",
        "military-history"
      ],
      "rating": 4.13,
      "ratings": 5950,
      "reviews": 285
    },
    {
      "title": "Vietnam: An Epic Tragedy, 1945-1975",
      "url": "https://www.goodreads.com/book/show/36099654-vietnam",
      "id": "57683946",
      "cover_url": "https://images-na.ssl-images-amazon.com/images/S/compressed.photo.goodreads.com/books/1508784853i/36099654.jpg",
      "authors": [
        "Max Hastings"
      ],
      "genres": [
        "history",
        "non-fiction",
        "war",
        "military-history",
        "military-fiction",
        "american-history",
        "politics"
      ],
      "rating": 4.29,
      "ratings": 5921,
      "reviews": 583
    },
    {
      "title": "Catastrophe 1914: Europe Goes to War",
      "url": "https://www.goodreads.com/book/show/17412744-catastrophe-1914",
      "id": "24258097",
      "cover_url": "https://images-na.ssl-images-amazon.com/images/S/compressed.photo.goodreads.com/books/1375116229i/17412744.jpg",
      "authors": [
        "Max Hastings"
      ],
      "genres": [
        "history",
        "non-fiction",
        "war",
        "world-war-i",
        "military-history",
        "military-fiction",
        "european-history"
      ],
      "rating": 4.05,
      "ratings": 5870,
      "reviews": 521
    },
    {
      "title": "On Desperate Ground: The Marines at The Reservoir, the Korean War's Greatest Battle",
      "url": "https://www.goodreads.com/book/show/37922709-on-desperate-ground",
      "id": "59636540",
      "cover_url": "https://images-na.ssl-images-amazon.com/images/S/compressed.photo.goodreads.com/books/1523342083i/37922709.jpg",
      "authors": [
        "Hampton Sides"
      ],
      "genres": [
        "history",
        "non-fiction",
        "war",
        "military-fiction",
        "military-history",
        "american-history",
        "audiobook"
      ],
      "rating": 4.56,
      "ratings": 5759,
      "reviews": 716
    },
    {
      "title": "Walk in My Combat Boots: True Stories from America's Bravest Warriors",
      "url": "https://www.goodreads.com/book/show/53915317-walk-in-my-combat-boots",
      "id": "84271381",
      "cover_url": "https://images-na.ssl-images-amazon.com/images/S/compressed.photo.goodreads.com/books/1606104755i/53915317.jpg",
      "authors": [
        "James Patterson"
      ],
      "genres": [
        "non-fiction",
        "history",
        "military-fiction",
        "biography",
        "war",
        "military-history",
        "contemporary"
      ],
      "rating": 4.19,
      "ratings": 5688,
      "reviews": 433
    },
    {
      "title": "Masters of the Air: America's Bomber Boys Who Fought the Air War Against Nazi Germany",
      "url": "https://www.goodreads.com/book/show/71318.Masters_of_the_Air",
      "id": "69069",
      "cover_url": "https://images-na.ssl-images-amazon.com/images/S/compressed.photo.goodreads.com/books/1388186808i/71318.jpg",
      "authors": [
        "Donald L. Miller"
      ],
      "genres": [
        "history",
        "non-fiction",
        "world-war-ii",
        "war",
        "military-history",
        "military-fiction",
        "aviation"
      ],
      "rating": 4.06,
      "ratings": 5683,
      "reviews": 301
    },
    {
      "title": "Spearhead: An American Tank Gunner, His Enemy, and a Collision of Lives In World War II",
      "url": "https://www.goodreads.com/book/show/40360266-spearhead",
      "id": "62637865",
      "cover_url": "https://images-na.ssl-images-amazon.com/images/S/compressed.photo.goodreads.com/books/1543378126i/40360266.jpg",
      "authors": [
        "Adam Makos"
      ],
      "genres": [
        "history",
        "non-fiction",
        "world-war-ii",
        "war",
        "military-fiction",
        "military-history",
        "biography"
      ],
      "rating": 4.53,
      "ratings": 5636,
      "reviews": 684
    },
    {
      "title": "In the Company of Heroes: The Personal Story Behind Black Hawk Down",
      "url": "https://www.goodreads.com/book/show/115997.In_the_Company_of_Heroes",
      "id": "111719",
      "cover_url": "https://images-na.ssl-images-amazon.com/images/S/compressed.photo.goodreads.com/books/1349104259i/115997.jpg",
      "authors": [
        "Michael J. Durant"
      ],
      "genres": [
        "military-fiction",
        "history",
        "non-fiction",
        "war",
        "military-history",
        "biography",
        "memoir"
      ],
      "rating": 4.26,
      "ratings": 5588,
      "reviews": 182
    },
    {
      "title": "Overlord: D-Day and the Battle for Normandy",
      "url": "https://www.goodreads.com/book/show/55414.Overlord",
      "id": "2869272",
      "cover_url": "https://images-na.ssl-images-amazon.com/images/S/compressed.photo.goodreads.com/books/1385178036i/55414.jpg",
      "authors": [
        "Max Hastings"
      ],
      "genres": [
        "history",
        "non-fiction",
        "world-war-ii",
        "military-history",
        "war",
        "military-fiction",
        "american-history"
      ],
      "rating": 4.17,
      "ratings": 5575,
      "reviews": 133
    },
    {
      "title": "Sniper One: The Blistering True Story Of A British Battle Group Under Siege",
      "url": "https://www.goodreads.com/book/show/2439931.Sniper_One",
      "id": "2447125",
      "cover_url": "https://images-na.ssl-images-amazon.com/images/S/compressed.photo.goodreads.com/books/1312518053i/2439931.jpg",
      "authors": [
        "Dan Mills"
      ],
      "genres": [
        "military-fiction",
        "non-fiction",
        "war",
        "history",
        "biography",
        "military-history",
        "autobiography"
      ],
      "rating": 4.28,
      "ratings": 5527,
      "reviews": 224
    },
    {
      "title": "Six Days of War: June 1967 and the Making of the Modern Middle East",
      "url": "https://www.goodreads.com/book/show/225897.Six_Days_of_War",
      "id": "218796",
      "cover_url": "https://images-na.ssl-images-amazon.com/images/S/compressed.photo.goodreads.com/books/1388386025i/225897.jpg",
      "authors": [
        "Michael B. Oren"
      ],
      "genres": [
        "history",
        "non-fiction",
        "israel",
        "war",
        "military-history",
        "politics",
        "military-fiction"
      ],
      "rating": 4.16,
      "ratings": 5486,
      "reviews": 445
    },
    {
      "title": "The Third Reich at War",
      "url": "https://www.goodreads.com/book/show/3761596-the-third-reich-at-war",
      "id": "3805502",
      "cover_url": "https://images-na.ssl-images-amazon.com/images/S/compressed.photo.goodreads.com/books/1347666024i/3761596.jpg",
      "authors": [
        "Richard J. Evans"
      ],
      "genres": [
        "history",
        "non-fiction",
        "world-war-ii",
        "germany",
        "war",
        "european-history",
        "military-history"
      ],
      "rating": 4.37,
      "ratings": 5400,
      "reviews": 295
    },
    {
      "title": "Devotion: An Epic Story of Heroism, Friendship, and Sacrifice",
      "url": "https://www.goodreads.com/book/show/20708942-devotion",
      "id": "40030964",
      "cover_url": "https://images-na.ssl-images-amazon.com/images/S/compressed.photo.goodreads.com/books/1396228138i/20708942.jpg",
      "authors": [
        "Adam Makos"
      ],
      "genres": [
        "history",
        "non-fiction",
        "military-fiction",
        "war",
        "biography",
        "aviation",
        "military-history"
      ],
      "rating": 4.51,
      "ratings": 5398,
      "reviews": 691
    }
  ]
}
